Workbook
Name AdicoesLR: #REF!
Name AjNegativosRTT: #REF!
Name AjPositivosRTT: #REF!
Name Ano: #REF!
Name Dia: #REF!
Name Empresas: #REF!
Name ExclusoesLR: #REF!
Name Mês: #REF!
Name ReconImp: #REF!
Name WACC: DCF!$B$20

Sheet Sheet1

Sheet Cover
A1: SLC Agrícola (SLCE3) | G1: About the Company
A2: Financial model and valuation for educational purposes
B4: Tiago Cousseau | E4: May 2026
B5: LinkedIn
B8: Target Price | E8: =DCF!B38 -> 17.334818
B9: Current Price | E9: 17.5
B10: Upside | E10: =(E8-E9)/E8 -> -0.0095289361
B11: CoE | E11: =WACC -> 0.13628945
A13: Methodologies
B15: • DCF Valuation
B16: • Commodity Price Curve
B17: • FX Forecast
B18: • Planted Area Growth

Sheet DCF
A1: Discounted Cash Flow | H1: Methodologies
B2: 2026 | C2: 2027 | D2: 2028 | E2: 2029 | F2: 2030
B3: F | C3: F | D3: F | E3: F | F3: F
A4: Revenue | B4: ='Income Statement'!O18 -> 9360729 | C4: ='Income Statement'!P18 -> 11616585 | D4: ='Income Statement'!Q18 -> 12399655 | E4: ='Income Statement'!R18 -> 13848822 | F4: ='Income Statement'!S18 -> 14465023 | H4: • Expected Planted Area • Historical Yield • Commodities Curve
A6: Net Income | B6: ='Income Statement'!O69 -> 523085.83 | C6: ='Income Statement'!P69 -> 871637.21 | D6: ='Income Statement'!Q69 -> 976386.79 | E6: ='Income Statement'!R69 -> 1189460 | F6: ='Income Statement'!S69 -> 1266856.3 | H6: • Historical Crop Margin • Recent SG&A % of Revenue • Last Year Interest Rate • Historical APV lease liability/ha
A8: =_xlfn.UNICHAR(916) & " WC" -> Δ WC | B8: ='Income Statement'!O18*B9 -> 140410.94 | C8: ='Income Statement'!P18*C9 -> 174248.78 | D8: ='Income Statement'!Q18*D9 -> 185994.82 | E8: ='Income Statement'!R18*E9 -> 207732.33 | F8: ='Income Statement'!S18*F9 -> 216975.35 | H8: • Historical Geometric Mean % of revenue
A9: % of revenue Ex. | B9: 0.015 | C9: 0.015 | D9: 0.015 | E9: 0.015 | F9: 0.015
A11: Maintenance Capex | B11: ='▲ PPE'!AC118 -> 385111.08 | C11: ='▲ PPE'!AD118 -> 404366.63 | D11: ='▲ PPE'!AE118 -> 424584.97 | E11: ='▲ PPE'!AF118 -> 445814.21 | F11: ='▲ PPE'!AG118 -> 468104.92 | H11: • Recent Maintenance Capex / ha
A12: R$/ha | B12: 0.4 | C12: 0.4 | D12: 0.4 | E12: 0.4 | F12: 0.4
A14: Expansion Capex | B14: ='▲ PPE'!AC138 -> 346599.97 | C14: ='▲ PPE'!AD138 -> 363929.97 | D14: ='▲ PPE'!AE138 -> 382126.47 | E14: ='▲ PPE'!AF138 -> 401232.79 | F14: ='▲ PPE'!AG138 -> 252776.66 | H14: • Last Year Expansion Capex / Current Planted Area Change
A15: ="Expansion CapEx t-1 /" & _xlfn.UNICHAR(916) &"ha t" -> Expansion CapEx t-1 /Δha t | B15: 7.2 | C15: 7.2 | D15: 7.2 | E15: 7.2 | F15: 7.2
A17: Depreciation | B17: ='▲ PPE'!AC33 -> 426713.1 | C17: ='▲ PPE'!AD33 -> 445012.98 | D17: ='▲ PPE'!AE33 -> 464409.99 | E17: ='▲ PPE'!AF33 -> 484948.08 | F17: ='▲ PPE'!AG33 -> 506674.02 | H17: • Recent Normalized Depreciation
A18: % of PPE | B18: 0.06 | C18: 0.06 | D18: 0.06 | E18: 0.06 | F18: 0.06
A20: Cost of Equity | B20: =CoE!O30 -> 0.13628945 | C20: =CoE!P30 -> 0.13504277 | D20: =CoE!Q30 -> 0.13374957 | E20: =CoE!R30 -> 0.13230453 | F20: =CoE!S30 -> 0.13090323 | H20: • Flat Debt • Equity Based on Retained Earnings • Damodaran Unleveraged Beta
A22: Free Cash | B22: =(B6-B8-B11-B14+B17) -> 77676.946 | C22: =(C6-C8-C11-C14+C17) -> 374104.81 | D22: =(D6-D8-D11-D14+D17) -> 448090.53 | E22: =(E6-E8-E11-E14+E17) -> 619628.75 | F22: =(F6-F8-F11-F14+F17) -> 835673.43
A24: Discounting
B26: 1 | C26: 2 | D26: 3 | E26: 4 | F26: 5
A27: Free Cash PV | B27: =IF(B22<0,0,B22/(1+B20)^B26) -> 68360.175 | C27: =IF(C22<0,0,C22/(1+C20)^C26) -> 290381.43 | D27: =IF(D22<0,0,D22/(1+D20)^D26) -> 307478.22 | E27: =IF(E22<0,0,E22/(1+E20)^E26) -> 376945.52 | F27: =IF(F22<0,0,F22/(1+F20)^F26) -> 451761.66
A28: Perpetuity | F28: =(F22*(1+B31))/(F20-B31) -> 8530387.3
A29: Perpetuity PV | F29: =F28/(DCF!B20+1)^F26 -> 4503227.3
A31: Terminal Growth | B31: 0.03
A33: Equity Value | B33: =SUM(B27:F27,F29) -> 5998154.3
A34: Cash and Cash Equivalents | B34: ='Balance Sheet'!N4 -> 2647586
A36: Shares | B36: 498750
A38: Equity per Share | B38: =SUM(B33:B34)/B36 -> 17.334818

Sheet Income Statement
A1: Income Statement
A2: (R$ thud) | B2: 2013 | C2: =SUM(B2+1) -> 2014 | D2: =SUM(C2+1) -> 2015 | E2: =SUM(D2+1) -> 2016 | F2: =SUM(E2+1) -> 2017 | G2: =SUM(F2+1) -> 2018 | H2: =SUM(G2+1) -> 2019 | I2: =SUM(H2+1) -> 2020 | J2: =SUM(I2+1) -> 2021 | ... S2: =SUM(R2+1) -> 2030
B3: A | C3: A | D3: A | E3: A | F3: A | G3: A | H3: A | I3: A | J3: A | K3: A | L3: A | M3: A | N3: A | O3: F | P3: F | Q3: F | R3: F | S3: F
A4: REVENUE
A5: Cotton lint | B5: 553635 | C5: 652524 | D5: 812693 | E5: 749417 | F5: 745772 | G5: 1088621 | H5: 1212573 | I5: 1697671 | J5: 2087461 | K5: 2930972 | L5: 2189209 | M5: 3568362 | N5: 3344618 | O5: =('Income by Crop'!O5*'Income by Crop'!O9)/1000 -> 3914909.8 | P5: =('Income by Crop'!P5*'Income by Crop'!P9)/1000 -> 4984930.9 | Q5: =('Income by Crop'!Q5*'Income by Crop'!Q9)/1000 -> 5133580.7 | R5: =('Income by Crop'!R5*'Income by Crop'!R9)/1000 -> 5756454.1 | S5: =('Income by Crop'!S5*'Income by Crop'!S9)/1000 -> 5942842.9
A6: Cottonseed | B6: 83077 | C6: 82043 | D6: 85019 | E6: 98902 | F6: 104375 | G6: 80496 | H6: 77154 | I6: 156269 | J6: 348928 | K6: 380070 | L6: 349283 | M6: 320811 | N6: 386901 | O6: =('Income by Crop'!O18*'Income by Crop'!O20)/1000 -> 462087.71 | P6: =('Income by Crop'!P18*'Income by Crop'!P20)/1000 -> 588385.29 | Q6: =('Income by Crop'!Q18*'Income by Crop'!Q20)/1000 -> 605930.84 | R6: =('Income by Crop'!R18*'Income by Crop'!R20)/1000 -> 679450.32 | S6: =('Income by Crop'!S18*'Income by Crop'!S20)/1000 -> 701450.31
A7: Soybean | B7: 328348 | C7: 478022 | D7: 634055 | E7: 583990 | F7: 720879 | G7: 875235 | H7: 1036218 | I7: 1291803 | J7: 1673697 | K7: 2973363 | L7: 3055726 | M7: 2092605 | N7: 2749065 | O7: =('Income by Crop'!O32*'Income by Crop'!O36)/1000 -> 3551190.7 | P7: =('Income by Crop'!P32*'Income by Crop'!P36)/1000 -> 4372079.8 | Q7: =('Income by Crop'!Q32*'Income by Crop'!Q36)/1000 -> 4783138.7 | R7: =('Income by Crop'!R32*'Income by Crop'!R36)/1000 -> 5349944.9 | S7: =('Income by Crop'!S32*'Income by Crop'!S36)/1000 -> 5645529.4
A8: Corn | B8: 99224 | C8: 111950 | D8: 121877 | E8: 164514 | F8: 152733 | G8: 146151 | H8: 253376 | I8: 383504 | J8: 518078 | K8: 710473 | L8: 846036 | M8: 523883 | N8: 1035234 | O8: =('Income by Crop'!O45*'Income by Crop'!O49)/1000 -> 1125058.2 | P8: =('Income by Crop'!P45*'Income by Crop'!P49)/1000 -> 1368615.6 | Q8: =('Income by Crop'!Q45*'Income by Crop'!Q49)/1000 -> 1559302.2 | R8: =('Income by Crop'!R45*'Income by Crop'!R49)/1000 -> 1729385.1 | S8: =('Income by Crop'!S45*'Income by Crop'!S49)/1000 -> 1824933.6
A9: Coffee | B9: 9145 | C9: 5334
A10: Sugarcane | C10: 2556
A11: Cattle Herd | I11: 29528 | J11: 59377 | K11: 110862 | L11: 121007 | M11: 202280 | N11: 383851 | O11: =('Income by Crop'!O60*'Income by Crop'!O64)/1000 -> 307482.62 | P11: =('Income by Crop'!P60*'Income by Crop'!P64)/1000 -> 302573.61 | Q11: =('Income by Crop'!Q60*'Income by Crop'!Q64)/1000 -> 317702.29 | R11: =('Income by Crop'!R60*'Income by Crop'!R64)/1000 -> 333587.41 | S11: =('Income by Crop'!S60*'Income by Crop'!S64)/1000 -> 350266.78
A12: Seeds | N12: 296096
A13: Others | B13: 15421 | C13: 29894 | D13: 59480 | E13: 26361 | F13: 23141 | G13: 39483 | H13: 72874 | I13: 70379 | J13: 261620 | K13: 272919 | L13: 61390 | M13: 92968 | N13: 129120
A15: Hedge Result | B15: -53622 | C15: -26319 | D15: =-231373 -> -231373 | E15: -21239 | F15: 111154 | G15: -130809 | H15: =-116290 -> -116290 | I15: -531607 | J15: =-585951 -> -585951 | K15: -5625 | L15: 607932 | M15: 114855 | N15: 228262
A16: Biological Assets | B16: 146292 | C16: 163171 | D16: 279830 | E16: 57704 | F16: 361847 | G16: 724291 | H16: 504751 | I16: 775534 | J16: 1961159 | K16: 2216676 | L16: 1891541 | M16: 887863 | N16: 1206067
A18: Revenue Ex. Biological Assets | B18: =SUM(B5:B15) -> 1035228 | C18: =SUM(C5:C15) -> 1336004 | D18: =SUM(D5:D15) -> 1481751 | E18: =SUM(E5:E15) -> 1601945 | F18: =SUM(F5:F15) -> 1858054 | G18: =SUM(G5:G15) -> 2099177 | H18: =SUM(H5:H15) -> 2535905 | I18: =SUM(I5:I15) -> 3097547 | ... N18: =SUM(N5:N15) -> 8553147 | O18: =SUM(O5:O16) -> 9360729 | P18: =SUM(P5:P16) -> 11616585 | Q18: =SUM(Q5:Q16) -> 12399655 | R18: =SUM(R5:R16) -> 13848822 | S18: =SUM(S5:S16) -> 14465023
A19: Total Revenue | B19: =SUM(B5:B16) -> 1181520 | C19: =SUM(C5:C16) -> 1499175 | D19: =SUM(D5:D16) -> 1761581 | E19: =SUM(E5:E16) -> 1659649 | F19: =SUM(F5:F16) -> 2219901 | G19: =SUM(G5:G16) -> 2823468 | H19: =SUM(H5:H16) -> 3040656 | I19: =SUM(I5:I16) -> 3873081 | ... N19: =SUM(N5:N16) -> 9759214
A21: COGS
A22: Cotton lint | B22: 379091 | C22: 424043 | D22: =501326 -> 501326 | E22: 629116 | F22: =481841 -> 481841 | G22: 567966 | H22: =762874 -> 762874 | I22: 945782 | J22: =1082365 -> 1082365 | K22: 1831639 | L22: =1636704 -> 1636704 | M22: 2204939 | N22: 2343345 | O22: =('Income by Crop'!O5*'Income by Crop'!O11*-1)/1000 -> 2583840.5 | P22: =('Income by Crop'!P5*'Income by Crop'!P11*-1)/1000 -> 3290054.4 | Q22: =('Income by Crop'!Q5*'Income by Crop'!Q11*-1)/1000 -> 3388163.3 | R22: =('Income by Crop'!R5*'Income by Crop'!R11*-1)/1000 -> 3799259.7 | S22: =('Income by Crop'!S5*'Income by Crop'!S11*-1)/1000 -> 3922276.3
A23: Cottonseed | B23: 58920 | C23: 61891 | D23: =64080 -> 64080 | E23: 97913 | F23: =75483 -> 75483 | G23: 52980 | H23: =61257 -> 61257 | I23: 98128 | J23: =133245 -> 133245 | K23: 140849 | L23: =205003 -> 205003 | M23: 227896 | N23: 229100 | O23: =('Income by Crop'!O18*'Income by Crop'!O22*-1)/1000 -> 328183.9 | P23: =('Income by Crop'!P18*'Income by Crop'!P22*-1)/1000 -> 417882.95 | Q23: =('Income by Crop'!Q18*'Income by Crop'!Q22*-1)/1000 -> 430344.16 | R23: =('Income by Crop'!R18*'Income by Crop'!R22*-1)/1000 -> 482559.16 | S23: =('Income by Crop'!S18*'Income by Crop'!S22*-1)/1000 -> 498183.99
A24: Soybean | B24: 259742 | C24: 366835 | D24: =419781 -> 419781 | E24: 463229 | F24: =506506 -> 506506 | G24: 567844 | H24: =644331 -> 644331 | I24: 697641 | J24: =793574 -> 793574 | K24: 1449659 | L24: =1634559 -> 1634559 | M24: 1599801 | N24: 1772371 | O24: =('Income by Crop'!O32*'Income by Crop'!O38*-1)/1000 -> 2414809.7 | P24: =('Income by Crop'!P32*'Income by Crop'!P38*-1)/1000 -> 2973014.3 | Q24: =('Income by Crop'!Q32*'Income by Crop'!Q38*-1)/1000 -> 3252534.3 | R24: =('Income by Crop'!R32*'Income by Crop'!R38*-1)/1000 -> 3637962.6 | S24: =('Income by Crop'!S32*'Income by Crop'!S38*-1)/1000 -> 3838960
A25: Corn | B25: 90679 | C25: 90674 | D25: =81088 -> 81088 | E25: 106401 | F25: =128920 -> 128920 | G25: 133109 | H25: =198182 -> 198182 | I25: 230112 | J25: =420625 -> 420625 | K25: 542399 | L25: =693868 -> 693868 | M25: 424994 | N25: 678447 | O25: =('Income by Crop'!O45*'Income by Crop'!O51*-1)/1000 -> 765039.56 | P25: =('Income by Crop'!P45*'Income by Crop'!P51*-1)/1000 -> 930658.6 | Q25: =('Income by Crop'!Q45*'Income by Crop'!Q51*-1)/1000 -> 1060325.5 | R25: =('Income by Crop'!R45*'Income by Crop'!R51*-1)/1000 -> 1175981.9 | S25: =('Income by Crop'!S45*'Income by Crop'!S51*-1)/1000 -> 1240954.9
A26: Coffee | B26: 3392 | C26: 6032
A27: Sugarcane | C27: 927
A28: Cattle Heard | I28: 25027 | J28: =53800 -> 53800 | K28: 119413 | L28: =143966 -> 143966 | M28: 184773 | N28: 343489 | O28: =('Income by Crop'!O60*'Income by Crop'!O66*-1)/1000 -> 270798.91 | P28: =('Income by Crop'!P60*'Income by Crop'!P66*-1)/1000 -> 266475.55 | Q28: =('Income by Crop'!Q60*'Income by Crop'!Q66*-1)/1000 -> 279799.33 | R28: =('Income by Crop'!R60*'Income by Crop'!R66*-1)/1000 -> 293789.3 | S28: =('Income by Crop'!S60*'Income by Crop'!S66*-1)/1000 -> 308478.76
A29: Seeds | N29: 84832
A30: Others | B30: 14384 | C30: 23088 | D30: =34915 -> 34915 | E30: 31589 | F30: =22555 -> 22555 | G30: 36335 | H30: =66562 -> 66562 | I30: 55096 | J30: =167682 -> 167682 | K30: 136771 | L30: =100671 -> 100671 | M30: 127279 | N30: 161490
A32: Realized Biological Assets | B32: 114026 | C32: 192600 | D32: =227270 -> 227270 | E32: 84933 | F32: =327300 -> 327300 | G32: 619276 | H32: =524266 -> 524266 | I32: 750996 | J32: =1425434 -> 1425434 | K32: 2237681 | L32: =2086659 -> 2086659 | M32: 726219 | N32: 1217211
A34: COGS Ex. Biological Assets | B34: =SUM(B22:B30) -> 806208 | C34: =SUM(C22:C30) -> 973490 | D34: =SUM(D22:D30) -> 1101190 | E34: =SUM(E22:E30) -> 1328248 | F34: =SUM(F22:F30) -> 1215305 | G34: =SUM(G22:G30) -> 1358234 | H34: =SUM(H22:H30) -> 1733206 | I34: =SUM(I22:I30) -> 2051786 | ... S34: =SUM(S22:S30) -> 9808853.9
A35: Total COGS | B35: =SUM(B22:B32) -> 920234 | C35: =SUM(C22:C32) -> 1166090 | D35: =SUM(D22:D32) -> 1328460 | E35: =SUM(E22:E32) -> 1413181 | F35: =SUM(F22:F32) -> 1542605 | G35: =SUM(G22:G32) -> 1977510 | H35: =SUM(H22:H32) -> 2257472 | I35: =SUM(I22:I32) -> 2802782 | ... N35: =SUM(N22:N32) -> 6830285
A37: Gross Profit | B37: =(B19-B35) -> 261286 | C37: =(C19-C35) -> 333085 | D37: =(D19-D35) -> 433121 | E37: =(E19-E35) -> 246468 | F37: =(F19-F35) -> 677296 | G37: =(G19-G35) -> 845958 | H37: =(H19-H35) -> 783184 | I37: =(I19-I35) -> 1070299 | ... N37: =(N19-N35) -> 2928929
A38: Gross Profit Ex Bio | B38: =B18-B34 -> 229020 | C38: =C18-C34 -> 362514 | D38: =D18-D34 -> 380561 | E38: =E18-E34 -> 273697 | F38: =F18-F34 -> 642749 | G38: =G18-G34 -> 740943 | H38: =H18-H34 -> 802699 | I38: =I18-I34 -> 1045761 | ... S38: =S18-S34 -> 4656169.1
A40: Sales Expenses | B40: -63991 | C40: -85335 | D40: -92070 | E40: -97589 | F40: -90206 | G40: -118674 | H40: -152972 | I40: -173964 | J40: -212559 | K40: -379664 | L40: -388859 | M40: -495108 | N40: -632312
A41: General & Administrative (G&A) | B41: -39272 | C41: -37078 | D41: -39769 | E41: -42894 | F41: -44832 | G41: -51573 | H41: -63236 | I41: -70058 | J41: -124286 | K41: -175815 | L41: -195892 | M41: -209059 | N41: -255715
A42: Profit Sharing | B42: -8457 | C42: -16658 | D42: -18668 | E42: -16193 | F42: -41204 | G42: -49941 | H42: -39915 | I42: -60110 | J42: -117163 | K42: -108789 | L42: -112868 | M42: -82179 | N42: -85638
A43: Other Operating Income / (Expenses) | B43: 913 | C43: -3217 | D43: 2884 | E43: 20523 | F43: 92399 | G43: 31987 | H43: 31651 | I43: 14763 | J43: 134563 | K43: 64123 | L43: 12106 | M43: -8228 | N43: -142703
A45: Total SG&A | B45: =SUM(B40:B43) -> -110807 | C45: =SUM(C40:C43) -> -142288 | D45: =SUM(D40:D43) -> -147623 | E45: =SUM(E40:E43) -> -136153 | F45: =SUM(F40:F43) -> -83843 | G45: =SUM(G40:G43) -> -188201 | H45: =SUM(H40:H43) -> -224472 | I45: =SUM(I40:I43) -> -289369 | ... N45: =SUM(N40:N43) -> -1116368 | O45: =O18*O46 -> -1029680.2 | P45: =P18*P46 -> -1277824.4 | Q45: =Q18*Q46 -> -1363962 | R45: =R18*R46 -> -1523370.4 | S45: =S18*S46 -> -1591152.5
A46: % of Revenue Ex bio | B46: =B45/B18 -> -0.10703632 | C46: =C45/C18 -> -0.10650268 | D46: =D45/D18 -> -0.0996274 | E46: =E45/E18 -> -0.084992306 | F46: =F45/F18 -> -0.045124092 | G46: =G45/G18 -> -0.08965466 | H46: =H45/H18 -> -0.088517511 | I46: =I45/I18 -> -0.09341876 | ... N46: =N45/N18 -> -0.13052132 | O46: -0.11 | P46: -0.11 | Q46: -0.11 | R46: -0.11 | S46: -0.11
A48: EBIT | B48: =B37+B45 -> 150479 | C48: =C37+C45 -> 190797 | D48: =D37+D45 -> 285498 | E48: =E37+E45 -> 110315 | F48: =F37+F45 -> 593453 | G48: =G37+G45 -> 657757 | H48: =H37+H45 -> 558712 | I48: =I37+I45 -> 780930 | ... N48: =N37+N45 -> 1812561
A49: EBIT Ex Bio | B49: =B38+B45 -> 118213 | C49: =C38+C45 -> 220226 | D49: =D38+D45 -> 232938 | E49: =E38+E45 -> 137544 | F49: =F38+F45 -> 558906 | G49: =G38+G45 -> 552742 | H49: =H38+H45 -> 578227 | I49: =I38+I45 -> 756392 | ... S49: =S38+S45 -> 3065016.6
A51: FINANCIAL RESULT
A52: Interest | B52: -36171 | C52: -68098 | D52: 35859 | E52: =-194915 -> -194915 | F52: -94074 | G52: =-77661 -> -77661 | H52: -101197 | I52: =-53636 -> -53636 | J52: -98269 | K52: =-459171 -> -459171 | L52: -454331 | M52: =-517399 -> -517399 | N52: -827999 | O52: =CoE!O7 -> -826926.39 | P52: =CoE!P7 -> -826926.39 | Q52: =CoE!Q7 -> -826926.39 | R52: =CoE!R7 -> -826926.39 | S52: =CoE!S7 -> -826926.39
A53: FX Variation | B53: -3257 | C53: =-32255 -> -32255 | D53: -145583 | E53: 93487 | F53: 10754 | G53: 9810 | H53: 5940 | I53: 28775 | J53: -55731 | K53: 58533 | L53: 65751 | M53: -160181 | N53: 75379
A54: Monetary Variation | B54: 17748 | C54: 1737 | D54: -1219 | E54: =-1037 -> -1037 | F54: -1929 | G54: -14 | H54: 139 | I54: 0 | J54: -121 | K54: -155 | L54: 4217 | M54: 10 | N54: 2585
A55: APVLiability Lease. (IFRS16) | B55: 0 | C55: 0 | D55: 0 | E55: 0 | F55: 0 | G55: 0 | H55: -47607 | I55: =-61106 -> -61106 | J55: -175149 | K55: =-280423 -> -280423 | L55: -283004 | M55: =-305778 -> -305778 | N55: -331963 | O55: ='Planted Area'!O52 -> -415919.97 | P55: ='Planted Area'!P52 -> -436715.96 | Q55: ='Planted Area'!Q52 -> -458551.76 | R55: ='Planted Area'!R52 -> -481479.35 | S55: ='Planted Area'!S52 -> -505553.32
A56: APV Securities payable | B56: 0 | C56: 0 | D56: 0 | E56: 0 | F56: 0 | G56: 0 | H56: 0 | I56: 0 | J56: 0 | K56: 0 | L56: -29795 | M56: =-23802 -> -23802 | N56: -54462
A57: Other financial revenue (expenses) | B57: -3215 | C57: =-3110 -> -3110 | D57: -7901 | E57: =-12011 -> -12011 | F57: -7214 | G57: =-4811 -> -4811 | H57: -1325 | I57: =-5783 -> -5783 | J57: -20610 | K57: =-18252 -> -18252 | L57: -14114 | M57: 8216 | N57: 37599 | O57: =O18*O59 -> -28082.187 | P57: =P18*P59 -> -34849.756 | Q57: =Q18*Q59 -> -37198.964 | R57: =R18*R59 -> -41546.466 | S57: =S18*S59 -> -43395.069
A58: Net Financial Result | B58: =SUM(B52:B57) -> -24895 | C58: =SUM(C52:C57) -> -101726 | D58: =SUM(D52:D57) -> -118844 | E58: =SUM(E52:E57) -> -114476 | F58: =SUM(F52:F57) -> -92463 | G58: =SUM(G52:G57) -> -72676 | H58: =SUM(H52:H57) -> -144050 | I58: =SUM(I52:I57) -> -91750 | ... S58: =SUM(S52:S57) -> -1375874.8
A59: Others(FX, Monetary, Securities, Other) % of Rev Ex | B59: =(B57+B56+B54+B53)/B18 -> 0.010892287 | C59: =(C57+C56+C54+C53)/C18 -> -0.025170583 | D59: =(D57+D56+D54+D53)/D18 -> -0.10440553 | E59: =(E57+E56+E54+E53)/E18 -> 0.050213334 | F59: =(F57+F56+F54+F53)/F18 -> 0.00086703616 | G59: =(G57+G56+G54+G53)/G18 -> 0.0023747402 | H59: =(H57+H56+H54+H53)/H18 -> 0.0018746759 | I59: =(I57+I56+I54+I53)/I18 -> 0.0074226477 | ... N59: =(N57+N56+N54+N53)/N18 -> 0.0071436864 | O59: =$B$60 -> -0.003 | P59: =$B$60 -> -0.003 | Q59: =$B$60 -> -0.003 | R59: =$B$60 -> -0.003 | S59: =$B$60 -> -0.003
A60: Assumption | B60: -0.003
A61: PROFIT BEFORE TAXES | B61: =B48+B58 -> 125584 | C61: =C48+C58 -> 89071 | D61: =D48+D58 -> 166654 | E61: =E48+E58 -> -4161 | F61: =F48+F58 -> 500990 | G61: =G48+G58 -> 585081 | H61: =H48+H58 -> 414662 | I61: =I48+I58 -> 689180 | ... N61: =N48+N58 -> 713700 | O61: =O49+O58 -> 697447.78 | P61: =P49+P58 -> 1162183 | Q61: =Q49+Q58 -> 1301849.1 | R61: =R49+R58 -> 1585946.7 | S61: =S49+S58 -> 1689141.8
A63: Current | B63: -46441 | C63: -43520 | D63: -33038 | E63: -27061 | F63: -77161 | G63: -97023 | H63: -90856 | I63: =-111392 -> -111392 | J63: -174507 | K63: =-544401 -> -544401 | L63: -320959 | M63: =-1556 -> -1556 | N63: -209830
A64: Deferred | B64: 17460 | C64: 24591 | D64: -12445 | E64: 46863 | F64: -54567 | G64: =-81557 -> -81557 | H64: -8765 | I64: =-66839 -> -66839 | J64: -255544 | K64: 75309 | L64: 35034 | M64: -30937 | N64: 61362
A65: Taxes | B65: =SUM(B63:B64) -> -28981 | C65: =SUM(C63:C64) -> -18929 | D65: =SUM(D63:D64) -> -45483 | E65: =SUM(E63:E64) -> 19802 | F65: =SUM(F63:F64) -> -131728 | G65: =SUM(G63:G64) -> -178580 | H65: =SUM(H63:H64) -> -99621 | I65: =SUM(I63:I64) -> -178231 | ... N65: =SUM(N63:N64) -> -148468 | O65: =O61*O66 -> -174361.94 | P65: =P61*P66 -> -290545.74 | Q65: =Q61*Q66 -> -325462.26 | R65: =R61*R66 -> -396486.67 | S65: =S61*S66 -> -422285.45
A66: Tax % | B66: =B65/B61 -> -0.23076984 | C66: =C65/C61 -> -0.21251586 | D66: =D65/D61 -> -0.27291874 | E66: =E65/E61 -> -4.7589522 | F66: =F65/F61 -> -0.26293539 | G66: =G65/G61 -> -0.3052227 | H66: =H65/H61 -> -0.24024627 | I66: =I65/I61 -> -0.25861313 | ... N66: =N65/N61 -> -0.20802578 | O66: ='Income Statement'!$B$67*-1 -> -0.25 | P66: ='Income Statement'!$B$67*-1 -> -0.25 | Q66: ='Income Statement'!$B$67*-1 -> -0.25 | R66: ='Income Statement'!$B$67*-1 -> -0.25 | S66: ='Income Statement'!$B$67*-1 -> -0.25
A67: Tax Rate | B67: 0.25
A69: NET INCOME | B69: =B61+B65 -> 96603 | C69: =C61+C65 -> 70142 | D69: =D61+D65 -> 121171 | E69: =E61+E65 -> 15641 | F69: =F61+F65 -> 369262 | G69: =G61+G65 -> 406501 | H69: =H61+H65 -> 315041 | I69: =I61+I65 -> 510949 | ... S69: =S61+S65 -> 1266856.3
A70: ▲% | C70: =(C69-B69)/B69 -> -0.27391489 | D70: =(D69-C69)/C69 -> 0.72750991 | E70: =(E69-D69)/D69 -> -0.87091796 | F70: =(F69-E69)/E69 -> 22.608593 | G70: =(G69-F69)/F69 -> 0.1008471 | H70: =(H69-G69)/G69 -> -0.2249933 | I70: =(I69-H69)/H69 -> 0.62184922 | J70: =(J69-I69)/I69 -> 1.2473241 | ... S70: =(S69-R69)/R69 -> 0.065068464
A71: NET INCOME (Ex. Biological Assets) | B71: =B69+B32-B16 -> 64337 | C71: =C69+C32-C16 -> 99571 | D71: =D69+D32-D16 -> 68611 | E71: =E69+E32-E16 -> 42870 | F71: =F69+F32-F16 -> 334715 | G71: =G69+G32-G16 -> 301486 | H71: =H69+H32-H16 -> 334556 | I71: =I69+I32-I16 -> 486411 | ... N71: =N69+N32-N16 -> 576376 | O71: =O61+O65 -> 523085.83 | P71: =P61+P65 -> 871637.21 | Q71: =Q61+Q65 -> 976386.79 | R71: =R61+R65 -> 1189460 | S71: =S61+S65 -> 1266856.3
C72: =(C71-B71)/B71 -> 0.54764754 | D72: =(D71-C71)/C71 -> -0.31093391 | E72: =(E71-D71)/D71 -> -0.37517308 | F72: =(F71-E71)/E71 -> 6.8076744 | G72: =(G71-F71)/F71 -> -0.099275503 | H72: =(H71-G71)/G71 -> 0.10969 | I72: =(I71-H71)/H71 -> 0.45390009 | J72: =(J71-I71)/I71 -> 0.25931157 | ... S72: =(S71-R71)/R71 -> 0.065068464
A97: Depreciation | B97: 115516 | C97: 99919 | D97: 106803 | E97: 104242 | F97: 91506 | G97: 111231 | H97: 105810 | I97: 119686 | J97: 145870 | K97: 177814 | L97: 219688 | M97: 286202 | N97: 380591
A98: ROU | H98: 43336 | I98: 73663 | J98: 133287 | K98: 310743 | L98: 299542 | M98: 289102 | N98: 336263

Sheet Planted Area
A1: Planted Area
A2: Planted Area (ha) | B2: 2013/14 | C2: 2014/15 | D2: 2015/16 | E2: 2016/17 | F2: 2017/18 | G2: 2018/19 | H2: 2019/20 | I2: 2020/21 | J2: 2021/22 | K2: 2022/23 | L2: 2023/24 | M2: 2024/25 | N2: 2025/26 | O2: 2026/27 | P2: 2027/28 | Q2: 2028/29 | R2: 2029/30 | S2: 2030/31
B3: A | C3: A | D3: A | E3: A | F3: A | G3: A | H3: A | I3: A | J3: A | K3: A | L3: A | M3: A | N3: A | O3: F | P3: F | Q3: F | R3: F | S3: F
A4: Cotton Lint 1 Crop | B4: 81019 | C4: 83680 | D4: 74404 | E4: 58886 | F4: 57832 | G4: 72852 | H4: 74054 | I4: 78011 | J4: 86357 | K4: 85823 | L4: 106698 | M4: 95460 | N4: 107464 | O4: =O16*O$11 -> 134601.01 | P4: =P16*P$11 -> 141331.06 | Q4: =Q16*Q$11 -> 148397.61 | R4: =R16*R$11 -> 155817.49 | S4: =S16*S$11 -> 163608.37
A5: Cotton Lint 2 Crop | B5: 12647 | C5: 14882 | D5: 19002 | E5: 28554 | F5: 37292 | G5: 50875 | H5: 51408 | I5: 31594 | J5: 90628 | K5: 76420 | L5: 82036 | M5: 83343 | N5: 84620 | O5: =O17*O$11 -> 108592.38 | P5: =P17*P$11 -> 114021.99 | Q5: =Q17*Q$11 -> 119723.09 | R5: =R17*R$11 -> 125709.25 | S5: =S17*S$11 -> 131994.71
A6: Soybean (commercial + seed) | B6: 184702 | C6: 208693 | D6: 212586 | E6: 230127 | F6: 230164 | G6: 243149 | H6: 235444 | I6: 229449 | J6: 334891 | K6: 346941 | L6: 320009 | M6: 377531 | N6: 424672 | O6: =O18*O$11 -> 482719.68 | P6: =P18*P$11 -> 506855.66 | Q6: =Q18*Q$11 -> 532198.44 | R6: =R18*R$11 -> 558808.37 | S6: =S18*S$11 -> 586748.79
A7: Corn 1 Crop | B7: 13575 | C7: 5127 | O7: =O19*O$11 -> 0 | P7: =P19*P$11 -> 0 | Q7: =Q19*Q$11 -> 0 | R7: =R19*R$11 -> 0 | S7: =S19*S$11 -> 0
A8: Corn 2 Crop | B8: 37190 | C8: 38280 | D8: 65681 | E8: 71790 | F8: 76931 | G8: 89311 | H8: 82392 | I8: 106470 | J8: 121633 | K8: 137585 | L8: 95167 | M8: 122748 | N8: 157370 | O8: =O20*O$11 -> 160036.23 | P8: =P20*P$11 -> 168038.04 | Q8: =Q20*Q$11 -> 176439.94 | R8: =R20*R$11 -> 185261.94 | S8: =S20*S$11 -> 194525.04
A9: Cattle Herd | I9: 3526 | J9: 4932 | K9: 3962 | L9: 5298 | M9: 5594 | N9: 8341 | O9: =O21*O$11 -> 8207.8345 | P9: =P21*P$11 -> 8618.2262 | Q9: =Q21*Q$11 -> 9049.1375 | R9: =R21*R$11 -> 9501.5944 | S9: =S21*S$11 -> 9976.6741
A10: Other | B10: 14435 | C10: 19363 | D10: 5587 | E10: 3564 | F10: 2228 | G10: 1912 | H10: 5270 | I10: 14117 | J10: 33505 | K10: 23653 | L10: 52134 | M10: 51230 | N10: 54732 | O10: =O22*O$11 -> 68620.577 | P10: =P22*P$11 -> 72051.606 | Q10: =Q22*Q$11 -> 75654.186 | R10: =R22*R$11 -> 79436.896 | S10: =S22*S$11 -> 83408.741
A11: Total | B11: =SUM(B4:B10) -> 343568 | C11: =SUM(C4:C10) -> 370025 | D11: =SUM(D4:D10) -> 377260 | E11: =SUM(E4:E10) -> 392921 | F11: =SUM(F4:F10) -> 404447 | G11: =SUM(G4:G10) -> 458099 | H11: =SUM(H4:H10) -> 448568 | I11: =SUM(I4:I10) -> 463167 | ... N11: =SUM(N4:N10) -> 837199 | O11: =O35 -> 962777.7 | P11: =P35 -> 1010916.6 | Q11: =Q35 -> 1061462.4 | R11: =R35 -> 1114535.5 | S11: =S35 -> 1170262.3
A12: Total %▲ | C12: =(C35-B35)/B35 -> 0.0770095 | D12: =(D35-C35)/C35 -> 0.01954187 | E12: =(E35-D35)/D35 -> 0.041520767 | F12: =(F35-E35)/E35 -> 0.029331596 | G12: =(G35-F35)/F35 -> 0.13265801 | H12: =(H35-G35)/G35 -> -0.020805546 | I12: =(I35-H35)/H35 -> 0.03254579 | J12: =(J35-I35)/I35 -> 0.45076398 | ... N12: =(N35-M35)/M35 -> 0.13764103 | O12: 0.15 | P12: 0.05 | Q12: 0.05 | R12: 0.05 | S12: 0.05
A15: Crop Composition
A16: Cotton Lint 1 Crop | B16: =B4/B$11 -> 0.23581649 | C16: =C4/C$11 -> 0.22614688 | D16: =D4/D$11 -> 0.19722207 | E16: =E4/E$11 -> 0.14986728 | F16: =F4/F$11 -> 0.14299031 | G16: =G4/G$11 -> 0.15903113 | H16: =H4/H$11 -> 0.1650898 | I16: =I4/I$11 -> 0.16842953 | ... N16: =N4/N$11 -> 0.12836136 | O16: 0.13980487 | P16: 0.13980487 | Q16: 0.13980487 | R16: 0.13980487 | S16: 0.13980487
A17: Cotton Lint 2 Crop | B17: =B5/B$11 -> 0.036810762 | C17: =C5/C$11 -> 0.040218904 | D17: =D5/D$11 -> 0.050368446 | E17: =E5/E$11 -> 0.072671097 | F17: =F5/F$11 -> 0.092204912 | G17: =G5/G$11 -> 0.11105678 | H17: =H5/H$11 -> 0.1146047 | I17: =I5/I$11 -> 0.068212977 | ... N17: =N5/N$11 -> 0.10107513 | O17: 0.1127907 | P17: 0.1127907 | Q17: 0.1127907 | R17: 0.1127907 | S17: 0.1127907
A18: Soybean (commercial + seed) | B18: =B6/B$11 -> 0.53759954 | C18: =C6/C$11 -> 0.56399703 | D18: =D6/D$11 -> 0.56349997 | E18: =E6/E$11 -> 0.58568262 | F18: =F6/F$11 -> 0.56908322 | G18: =G6/G$11 -> 0.53077828 | H18: =H6/H$11 -> 0.52487917 | I18: =I6/I$11 -> 0.49539151 | ... N18: =N6/N$11 -> 0.50725335 | O18: 0.50138228 | P18: 0.50138228 | Q18: 0.50138228 | R18: 0.50138228 | S18: 0.50138228
A19: Corn 1 Crop | B19: =B7/B$11 -> 0.039511829 | C19: =C7/C$11 -> 0.013855821 | D19: =D7/D$11 -> 0 | E19: =E7/E$11 -> 0 | F19: =F7/F$11 -> 0 | G19: =G7/G$11 -> 0 | H19: =H7/H$11 -> 0 | I19: =I7/I$11 -> 0 | ... N19: =N7/N$11 -> 0 | O19: 0 | P19: 0 | Q19: 0 | R19: 0 | S19: 0
A20: Corn 2 Crop | B20: =B8/B$11 -> 0.1082464 | C20: =C8/C$11 -> 0.10345247 | D20: =D8/D$11 -> 0.17410009 | E20: =E8/E$11 -> 0.18270848 | F20: =F8/F$11 -> 0.19021281 | G20: =G8/G$11 -> 0.19496004 | H20: =H8/H$11 -> 0.18367784 | I20: =I8/I$11 -> 0.22987389 | ... N20: =N8/N$11 -> 0.18797204 | O20: 0.16622345 | P20: 0.16622345 | Q20: 0.16622345 | R20: 0.16622345 | S20: 0.16622345
A21: Cattle | B21: =B9/B$11 -> 0 | C21: =C9/C$11 -> 0 | D21: =D9/D$11 -> 0 | E21: =E9/E$11 -> 0 | F21: =F9/F$11 -> 0 | G21: =G9/G$11 -> 0 | H21: =H9/H$11 -> 0 | I21: =I9/I$11 -> 0.0076128049 | ... N21: =N9/N$11 -> 0.0099629837 | O21: 0.0085251606 | P21: 0.0085251606 | Q21: 0.0085251606 | R21: 0.0085251606 | S21: 0.0085251606
A22: Other | B22: =B10/B$11 -> 0.042014972 | C22: =C10/C$11 -> 0.052328897 | D22: =D10/D$11 -> 0.014809415 | E22: =E10/E$11 -> 0.0090705256 | F22: =F10/F$11 -> 0.0055087564 | G22: =G10/G$11 -> 0.0041737703 | H22: =H10/H$11 -> 0.011748497 | I22: =I10/I$11 -> 0.030479287 | ... N22: =N10/N$11 -> 0.065375138 | O22: 0.071273542 | P22: 0.071273542 | Q22: 0.071273542 | R22: 0.071273542 | S22: 0.071273542
A23: Total | B23: =SUM(B16:B22) -> 1 | C23: =SUM(C16:C22) -> 1 | D23: =SUM(D16:D22) -> 1 | E23: =SUM(E16:E22) -> 1 | F23: =SUM(F16:F22) -> 1 | G23: =SUM(G16:G22) -> 1 | H23: =SUM(H16:H22) -> 1 | I23: =SUM(I16:I22) -> 1 | ... S23: =SUM(S16:S22) -> 1
A26: Ownership
A27: 80% of SLC Land Co | B27: =(B76+B82)*0.8 -> 27991.2 | C27: =(C76+C82)*0.8 -> 30612.8 | D27: =(D76+D82)*0.8 -> 28629.6 | E27: =(E76+E82)*0.8 -> 36442.4 | F27: =(F76+F82)*0.8 -> 37265.6 | G27: =(G76+G82)*0.8 -> 39578.4 | H27: =(H76+H82)*0.8 -> 39789.6 | I27: =(I76+I82)*0.8 -> 40124 | ... N27: =(N76+N82)*0.8 -> 0
A28: 50% of Joint Ventures | B28: =(B81+B75)*0.5 -> 15327.5 | C28: =(C81+C75)*0.5 -> 20993.5 | D28: =(D81+D75)*0.5 -> 24472.5 | E28: =(E81+E75)*0.5 -> 24017 | F28: =(F81+F75)*0.5 -> 22957 | G28: =(G81+G75)*0.5 -> 24033.5 | H28: =(H81+H75)*0.5 -> 25012 | I28: =(I81+I75)*0.5 -> 27910.5 | ... N28: =(N81+N75)*0.5 -> 69504.5
A29: Owned | B29: =B73+B79 -> 166538 | C29: =C73+C79 -> 173512 | D29: =D73+D79 -> 174125 | E29: =E73+E79 -> 177275 | F29: =F73+F79 -> 169175 | G29: =G73+G79 -> 173279 | H29: =H73+H79 -> 165257 | I29: =I73+I79 -> 161428 | ... N29: =N73+N79 -> 250272
A30: Total Owned | B30: =SUM(B27:B29) -> 209856.7 | C30: =SUM(C27:C29) -> 225118.3 | D30: =SUM(D27:D29) -> 227227.1 | E30: =SUM(E27:E29) -> 237734.4 | F30: =SUM(F27:F29) -> 229397.6 | G30: =SUM(G27:G29) -> 236890.9 | H30: =SUM(H27:H29) -> 230058.6 | I30: =SUM(I27:I29) -> 229462.5 | ... N30: =SUM(N27:N29) -> 319776.5 | O30: =O35*O38 -> 365855.53 | P30: =P35*P38 -> 384148.3 | Q30: =Q35*Q38 -> 403355.72 | R30: =R35*R38 -> 423523.5 | S30: =S35*S38 -> 444699.68
A31: Total Leased | B31: =B74+B80 -> 111386 | C31: =C74+C80 -> 116261 | D31: =D74+D80 -> 118400 | E31: =E74+E80 -> 122059 | F31: =F74+F80 -> 142775 | G31: =G74+G80 -> 187280 | H31: =H74+H80 -> 183550 | I31: =I74+I80 -> 195763 | ... N31: =N74+N80 -> 447917 | O31: =O35*O39 -> 519899.96 | P31: =P35*P39 -> 545894.96 | Q31: =Q35*Q39 -> 573189.7 | R31: =R35*R39 -> 601849.19 | S31: =S35*S39 -> 631941.65
A32: 20% of SLC Land Co | B32: =(B76+B82)*0.2 -> 6997.8 | C32: =(C76+C82)*0.2 -> 7653.2 | D32: =(D76+D82)*0.2 -> 7157.4 | E32: =(E76+E82)*0.2 -> 9110.6 | F32: =(F76+F82)*0.2 -> 9316.4 | G32: =(G76+G82)*0.2 -> 9894.6 | H32: =(H76+H82)*0.2 -> 9947.4 | I32: =(I76+I82)*0.2 -> 10031 | ... N32: =(N76+N82)*0.2 -> 0
A33: 50% of Joint Ventures | B33: =(B81+B75)*0.5 -> 15327.5 | C33: =(C81+C75)*0.5 -> 20993.5 | D33: =(D81+D75)*0.5 -> 24472.5 | E33: =(E81+E75)*0.5 -> 24017 | F33: =(F81+F75)*0.5 -> 22957 | G33: =(G81+G75)*0.5 -> 24033.5 | H33: =(H81+H75)*0.5 -> 25012 | I33: =(I81+I75)*0.5 -> 27910.5 | ... N33: =(N81+N75)*0.5 -> 69504.5
A34: Total Others | B34: =SUM(B32:B33) -> 22325.3 | C34: =SUM(C32:C33) -> 28646.7 | D34: =SUM(D32:D33) -> 31629.9 | E34: =SUM(E32:E33) -> 33127.6 | F34: =SUM(F32:F33) -> 32273.4 | G34: =SUM(G32:G33) -> 33928.1 | H34: =SUM(H32:H33) -> 34959.4 | I34: =SUM(I32:I33) -> 37941.5 | ... N34: =SUM(N32:N33) -> 69504.5 | O34: =O35*O40 -> 77022.216 | P34: =P35*P40 -> 80873.327 | Q34: =Q35*Q40 -> 84916.993 | R34: =R35*R40 -> 89162.843 | S34: =S35*S40 -> 93620.985
A35: Total Sum | B35: =SUM(B34,B31,B30) -> 343568 | C35: =SUM(C34,C31,C30) -> 370026 | D35: =SUM(D34,D31,D30) -> 377257 | E35: =SUM(E34,E31,E30) -> 392921 | F35: =SUM(F34,F31,F30) -> 404446 | G35: =SUM(G34,G31,G30) -> 458099 | H35: =SUM(H34,H31,H30) -> 448568 | I35: =SUM(I34,I31,I30) -> 463167 | ... N35: =SUM(N34,N31,N30) -> 837198 | O35: =N35*(1+O12) -> 962777.7 | P35: =O35*(1+P12) -> 1010916.6 | Q35: =P35*(1+Q12) -> 1061462.4 | R35: =Q35*(1+R12) -> 1114535.5 | S35: =R35*(1+S12) -> 1170262.3
A36: ▲ | C36: =C35-B35 -> 26458 | D36: =D35-C35 -> 7231 | E36: =E35-D35 -> 15664 | F36: =F35-E35 -> 11525 | G36: =G35-F35 -> 53653 | H36: =H35-G35 -> -9531 | I36: =I35-H35 -> 14599 | J36: =J35-I35 -> 208779 | ... S36: =S35-R35 -> 55726.777
A37: % Composition
A38: Owned | B38: =B30/B$35 -> 0.61081562 | C38: =C30/C$35 -> 0.60838509 | D38: =D30/D$35 -> 0.60231381 | E38: =E30/E$35 -> 0.60504376 | F38: =F30/F$35 -> 0.56718969 | G38: =G30/G$35 -> 0.51711726 | H38: =H30/H$35 -> 0.51287341 | I38: =I30/I$35 -> 0.49542066 | ... N38: =N30/N$35 -> 0.38196042 | O38: 0.38 | P38: 0.38 | Q38: 0.38 | R38: 0.38 | S38: 0.38
A39: Leased | B39: =B31/B$35 -> 0.32420365 | C39: =C31/C$35 -> 0.31419684 | D39: =D31/D$35 -> 0.31384441 | E39: =E31/E$35 -> 0.31064514 | F39: =F31/F$35 -> 0.35301375 | G39: =G31/G$35 -> 0.40881993 | H39: =H31/H$35 -> 0.40919103 | I39: =I31/I$35 -> 0.4226618 | ... N39: =N31/N$35 -> 0.53501919 | O39: 0.54 | P39: 0.54 | Q39: 0.54 | R39: 0.54 | S39: 0.54
A40: Others | B40: =B34/B$35 -> 0.064980732 | C40: =C34/C$35 -> 0.077418073 | D40: =D34/D$35 -> 0.083841784 | E40: =E34/E$35 -> 0.084311096 | F40: =F34/F$35 -> 0.079796561 | G40: =G34/G$35 -> 0.074062812 | H40: =H34/H$35 -> 0.077935564 | I40: =I34/I$35 -> 0.081917537 | ... N40: =N34/N$35 -> 0.083020385 | O40: 0.08 | P40: 0.08 | Q40: 0.08 | R40: 0.08 | S40: 0.08
A43: Expansion Capex Assumption
A44: Expansion Capex t-1 /▲ha t | C44: ='▲ PPE'!P138/C36 -> 5.0752069 | D44: ='▲ PPE'!Q138/D36 -> 11.298867 | E44: ='▲ PPE'!R138/E36 -> 5.6486035 | F44: ='▲ PPE'!S138/F36 -> -2.4384603 | G44: ='▲ PPE'!T138/G36 -> 0.55273852 | H44: ='▲ PPE'!U138/H36 -> -14.887316 | I44: ='▲ PPE'!V138/I36 -> 9.4022861 | J44: ='▲ PPE'!W138/J36 -> 0.30398309 | ... N44: ='▲ PPE'!AA138/N36 -> 7.4544875 | O44: =DCF!B15 -> 7.2 | P44: =DCF!C15 -> 7.2 | Q44: =DCF!D15 -> 7.2 | R44: =DCF!E15 -> 7.2 | S44: =DCF!F15 -> 7.2
A45: Median Ex Outliers | B45: =MEDIAN(C44:E44,I44:J44,M44:N44,G44) -> 6.5515455
A46: (Expansion Capex 2025A /▲ha 2026F)/Total ha 2025A | B46: =('▲ PPE'!AB138/'Planted Area'!O44)/N35 -> 0.22369546
A50: APV Lease Liability Assumption
A51: Total Leased | B51: =B31 -> 111386 | C51: =C31 -> 116261 | D51: =D31 -> 118400 | E51: =E31 -> 122059 | F51: =F31 -> 142775 | G51: =G31 -> 187280 | H51: =H31 -> 183550 | I51: =I31 -> 195763 | ... S51: =S31 -> 631941.65
A52: APV lease liability (thud) | B52: ='Income Statement'!B55 -> 0 | C52: ='Income Statement'!C55 -> 0 | D52: ='Income Statement'!D55 -> 0 | E52: ='Income Statement'!E55 -> 0 | F52: ='Income Statement'!F55 -> 0 | G52: ='Income Statement'!G55 -> 0 | H52: ='Income Statement'!H55 -> -47607 | I52: ='Income Statement'!I55 -> -61106 | ... N52: ='Income Statement'!N55 -> -331963 | O52: =O51*O54 -> -415919.97 | P52: =P51*P54 -> -436715.96 | Q52: =Q51*Q54 -> -458551.76 | R52: =R51*R54 -> -481479.35 | S52: =S51*S54 -> -505553.32
A54: APV lease liability (thud) / ha | B54: =B52/B51 -> 0 | C54: =C52/C51 -> 0 | D54: =D52/D51 -> 0 | E54: =E52/E51 -> 0 | F54: =F52/F51 -> 0 | G54: =G52/G51 -> 0 | H54: =H52/H51 -> -0.25936802 | I54: =I52/I51 -> -0.31214274 | ... N54: =N52/N51 -> -0.74112615 | O54: =$B$55 -> -0.8 | P54: =$B$55 -> -0.8 | Q54: =$B$55 -> -0.8 | R54: =$B$55 -> -0.8 | S54: =$B$55 -> -0.8
A55: APV lease liability (thud) / ha Assumption | B55: -0.8
A72: Area Mix
A73: Owned | B73: 127881 | C73: 129929 | D73: 124807 | E73: 118552 | F73: 108516 | G73: 111279 | H73: 111101 | I73: 110273 | J73: 111825 | K73: 122131.78 | L73: 128318 | M73: 211930 | N73: 174432
A74: Leased | B74: 94665 | C74: 100507 | D74: 93867 | E74: 97929 | F74: 106540 | G74: 130669 | H74: 129946 | I74: 135006 | J74: 250775 | K74: 231850.48 | L74: 222519 | M74: 230637 | N74: 292505
A75: Joint Ventures | B75: 30655 | C75: 40534 | D75: 41375 | E75: 39523 | F75: 38879 | G75: 39551 | H75: 40148 | I75: 41594 | J75: 41316 | K75: 41669.02 | L75: 41662 | M75: 48328 | N75: 90037
A76: SLC LandCo | B76: 29254 | C76: 30316 | D76: 30301 | E76: 35110 | F76: 34672 | G76: 34660 | H76: 32263 | I76: 35162 | J76: 44651 | K76: 49481.077 | L76: 51297 | M76: 0 | N76: 0
A77: 1st Crop Area | B77: =SUM(B73:B76) -> 282455 | C77: =SUM(C73:C76) -> 301286 | D77: =SUM(D73:D76) -> 290350 | E77: =SUM(E73:E76) -> 291114 | F77: =SUM(F73:F76) -> 288607 | G77: =SUM(G73:G76) -> 316159 | H77: =SUM(H73:H76) -> 313458 | I77: =SUM(I73:I76) -> 322035 | ... N77: =SUM(N73:N76) -> 556974
A79: Owned | B79: 38657 | C79: 43583 | D79: 49318 | E79: 58723 | F79: 60659 | G79: 62000 | H79: 54156 | I79: 51155 | J79: 54241 | K79: 63627.04 | L79: 52612 | M79: 87366 | N79: 75840
A80: Leased | B80: 16721 | C80: 15754 | D80: 24533 | E80: 24130 | F80: 36235 | G80: 56611 | H80: 53604 | I80: 60757 | J80: 138082 | K80: 130769.08 | L80: 124274 | M80: 117690 | N80: 155412
A81: Joint Ventures | C81: 1453 | D81: 7570 | E81: 8511 | F81: 7035 | G81: 8516 | H81: 9876 | I81: 14227 | J81: 14491 | K81: 13748.6 | L81: 18327 | M81: 39956 | N81: 48972
A82: SLC LandCo | B82: 5735 | C82: 7950 | D82: 5486 | E82: 10443 | F82: 11910 | G82: 14813 | H82: 17474 | I82: 14993 | J82: 16565 | K82: 21106.45 | L82: 22334 | M82: 0 | N82: 0
A83: 2nd Crop Area | B83: =SUM(B79:B82) -> 61113 | C83: =SUM(C79:C82) -> 68740 | D83: =SUM(D79:D82) -> 86907 | E83: =SUM(E79:E82) -> 101807 | F83: =SUM(F79:F82) -> 115839 | G83: =SUM(G79:G82) -> 141940 | H83: =SUM(H79:H82) -> 135110 | I83: =SUM(I79:I82) -> 141132 | ... N83: =SUM(N79:N82) -> 280224
A85: Total Area | B85: =SUM(B83,B77) -> 343568 | C85: =SUM(C83,C77) -> 370026 | D85: =SUM(D83,D77) -> 377257 | E85: =SUM(E83,E77) -> 392921 | F85: =SUM(F83,F77) -> 404446 | G85: =SUM(G83,G77) -> 458099 | H85: =SUM(H83,H77) -> 448568 | I85: =SUM(I83,I77) -> 463167 | ... N85: =SUM(N83,N77) -> 837198
C86: =(C85-B85)/B85 -> 0.0770095 | D86: =(D85-C85)/C85 -> 0.01954187 | E86: =(E85-D85)/D85 -> 0.041520767 | F86: =(F85-E85)/E85 -> 0.029331596 | G86: =(G85-F85)/F85 -> 0.13265801 | H86: =(H85-G85)/G85 -> -0.020805546 | I86: =(I85-H85)/H85 -> 0.03254579 | J86: =(J85-I85)/I85 -> 0.45076398 | ... N86: =(N85-M85)/M85 -> 0.13764103

Sheet Income by Crop
A1: Income by Crop | Y1: Yield
B2: 2013 | C2: =B2+1 -> 2014 | D2: =C2+1 -> 2015 | E2: =D2+1 -> 2016 | F2: =E2+1 -> 2017 | G2: =F2+1 -> 2018 | H2: =G2+1 -> 2019 | I2: =H2+1 -> 2020 | J2: =I2+1 -> 2021 | ... Q2: =P2+1 -> 2028 | R2: 2029 | S2: 2030 | Z2: 2013 | AA2: 2014 | AB2: 2015 | AC2: 2016 | AD2: 2017 | AE2: 2018 | AF2: 2019 | AG2: 2020 | AH2: 2021 | AI2: 2022 | AJ2: 2023 | AK2: 2024 | AL2: 2025 | AM2: 2026 | AN2: 2027 | AO2: 2028 | AP2: 2029 | AQ2: 2030
B3: A | C3: A | D3: A | E3: A | F3: A | G3: A | H3: A | I3: A | J3: A | K3: A | L3: A | M3: A | N3: A | O3: F | P3: F | Q3: F | R3: F | S3: F | Z3: A | AA3: A | AB3: A | AC3: A | AD3: A | AE3: A | AF3: A | AG3: A | AH3: A | AI3: A | AJ3: A | AK3: A | AL3: A | AM3: F | AN3: F | AO3: F | AP3: F | AQ3: F
A4: Cotton Lint Sold | Y4: Yield (ton/ha)
A5: Quantity Sold (Ton) | B5: 137437 | C5: 152796 | D5: 158183 | E5: 148429 | F5: 141126 | G5: 169673 | H5: 185374 | I5: 215965 | J5: 255993 | K5: 277222 | L5: 239303 | M5: 364238 | N5: 369328 | O5: ='Planted Area'!N4*'Income by Crop'!AM5+'Planted Area'!O5*'Income by Crop'!AM6 -> 424197.15 | P5: ='Planted Area'!O4*'Income by Crop'!AN5+'Planted Area'!P5*'Income by Crop'!AN6 -> 490879.94 | Q5: ='Planted Area'!P4*'Income by Crop'!AO5+'Planted Area'!Q5*'Income by Crop'!AO6 -> 518001.06 | R5: ='Planted Area'!Q4*'Income by Crop'!AP5+'Planted Area'!R5*'Income by Crop'!AP6 -> 546620.62 | S5: ='Planted Area'!R4*'Income by Crop'!AQ5+'Planted Area'!R5*'Income by Crop'!AQ6 -> 564319.7 | Y5: Cotton Lint 1st Crop | Z5: 1.758 | AA5: 1.522 | AB5: 1.25 | AC5: 1.619 | AD5: 1.929 | AE5: 1.685 | AF5: 1.842 | AG5: 1.913 | AH5: 1.682 | AI5: 2.019 | AJ5: 1.995 | AK5: 1.841 | AL5: 2.066 | AM5: =Z13*(1+$Z$19) -> 1.97717 | AN5: =AM5*(1+$Z$19) -> 1.9870558 | AO5: =AN5*(1+$Z$19) -> 1.9969911 | AP5: =AO5*(1+$Z$19) -> 2.0069761 | AQ5: =AP5*(1+$Z$19) -> 2.017011
A6: Net Revenue (R$ thousand) | B6: 553635 | C6: 652524 | D6: 812693 | E6: 749417 | F6: 745772 | G6: 1088621 | H6: 1212573 | I6: 1697671 | J6: 2383537 | K6: 2930972 | L6: 2189209 | M6: 3568362 | N6: 3344618 | Y6: Cotton Lint 2nd Crop | Z6: 1.545 | AA6: 1.671 | AB6: 1.389 | AC6: 1.57 | AD6: 1.622 | AE6: 1.611 | AF6: 1.749 | AG6: 1.689 | AH6: 1.305 | AI6: 1.863 | AJ6: 1.827 | AK6: 2.011 | AL6: 1.982 | AM6: =Z14*(1+$Z$19) -> 1.9497 | AN6: =AM6*(1+$Z$19) -> 1.9594485 | AO6: =AN6*(1+$Z$19) -> 1.9692457 | AP6: =AO6*(1+$Z$19) -> 1.979092 | AQ6: =AP6*(1+$Z$19) -> 1.9889874
A7: Hedhe Result (R$ thousand) | D7: -156717 | E7: -40092 | F7: 46005 | G7: -111011 | H7: -61699 | I7: -398374 | J7: -561891 | K7: -160865 | L7: 337690 | M7: 92514 | N7: 189964 | Y7: Soybean (commercial + seed) | Z7: 2.914 | AA7: 3.082 | AB7: 2.58 | AC7: 3.077 | AD7: 3.692 | AE7: 3.739 | AF7: 3.607 | AG7: 3.985 | AH7: 3.974 | AI7: 3.667 | AJ7: 3.264 | AK7: 3.961 | AL7: 4.036 | AM7: =Z15*(1+$Z$19) -> 3.772435 | AN7: =AM7*(1+$Z$19) -> 3.7912972 | AO7: =AN7*(1+$Z$19) -> 3.8102537 | AP7: =AO7*(1+$Z$19) -> 3.8293049 | AQ7: =AP7*(1+$Z$19) -> 3.8484515
A8: Hedge Adj. Net Revenue (R$ thousand) | D8: 655976 | E8: 709325 | F8: 791777 | G8: 977610 | H8: 1150874 | I8: 1299297 | J8: 1821646 | K8: 2770107 | L8: 2526899 | M8: 3660876 | N8: 3534582 | Y8: Corn 1st Crop | Z8: 8.345 | AA8: 5.708
A9: Unit Price (R$ / Ton) | B9: 4030 | C9: 4270 | D9: 4147 | E9: 4779 | F9: 5610 | G9: 5762 | H9: 6208 | I9: 6016 | J9: 7116 | K9: 9992 | L9: 10559 | M9: 10051 | N9: 9570 | O9: =Z45 -> 9228.9865 | P9: =AA45 -> 10155.092 | Q9: =AB45 -> 9910.3672 | R9: =AC45 -> 10530.986 | S9: =AD45 -> 10530.986 | Y9: Corn 2nd Crop | Z9: 7.516 | AA9: 7.029 | AB9: 5.378 | AC9: 6.877 | AD9: 5.715 | AE9: 7.095 | AF9: 7.385 | AG9: 5.88 | AH9: 6.303 | AI9: 7.588 | AJ9: 7.093 | AK9: 8.304 | AL9: 7.738 | AM9: =Z17*(1+$Z$19) -> 7.750225 | AN9: =AM9*(1+$Z$19) -> 7.7889761 | AO9: =AN9*(1+$Z$19) -> 7.827921 | AP9: =AO9*(1+$Z$19) -> 7.8670606 | AQ9: =AP9*(1+$Z$19) -> 7.9063959
A10: Total Cost (R$ thousand) | B10: -379091 | C10: -424043 | D10: -501326 | E10: -629116 | F10: -481841 | G10: -567966 | H10: -762874 | I10: -945782 | J10: -1220756 | K10: -1831639 | L10: -1636704 | M10: -2204939 | N10: -2343345 | Y10: Other
A11: Unit Cost (R$ / Ton) | B11: -2760 | C11: -2780 | D11: -3169 | E11: -4238 | F11: -3414 | G11: -3347 | H11: -4115 | I11: -4379 | J11: -4769 | K11: -6607 | L11: -6839 | M11: -6054 | N11: -6345 | O11: =(O9-O12)*-1 -> -6091.1311 | P11: =(P9-P12)*-1 -> -6702.3606 | Q11: =(Q9-Q12)*-1 -> -6540.8424 | R11: =(R9-R12)*-1 -> -6950.4508 | S11: =(S9-S12)*-1 -> -6950.4508
A12: Unit Margin (R$ / Ton) | B12: 1270 | C12: 1490 | D12: 978 | E12: 541 | F12: 2196 | G12: 2415 | H12: 2093 | I12: 1637 | J12: 2347 | K12: 3385 | L12: 3720 | M12: 3997 | N12: 3225 | O12: =O9*O13 -> 3137.8554 | P12: =P9*P13 -> 3452.7312 | Q12: =Q9*Q13 -> 3369.5249 | R12: =R9*R13 -> 3580.5353 | S12: =S9*S13 -> 3580.5353 | Y12: Average Yield (Last 3y)
A13: Margin % | B13: =B12/B9 -> 0.31513648 | C13: =C12/C9 -> 0.34894614 | D13: =D12/D9 -> 0.23583313 | E13: =E12/E9 -> 0.1132036 | F13: =F12/F9 -> 0.39144385 | G13: =G12/G9 -> 0.4191253 | H13: =H12/H9 -> 0.33714562 | I13: =I12/I9 -> 0.27210771 | ... N13: =N12/N9 -> 0.3369906 | O13: =$B$14 -> 0.34 | P13: =$B$14 -> 0.34 | Q13: =$B$14 -> 0.34 | R13: =$B$14 -> 0.34 | S13: =$B$14 -> 0.34 | Y13: Cotton Lint 1st Crop | Z13: =AVERAGE(AJ5:AL5) -> 1.9673333
A14: Margin Assumption | B14: 0.34 | Y14: Cotton Lint 2nd Crop | Z14: =AVERAGE(AJ6:AL6) -> 1.94
Y15: Soybean (commercial + seed) | Z15: =AVERAGE(AJ7:AL7) -> 3.7536667
Y16: Corn 1st Crop
A17: Cottonseed Sold | Y17: Corn 2nd Crop | Z17: =AVERAGE(AJ9:AL9) -> 7.7116667
A18: Quantity Sold (Ton) | B18: 159917 | C18: 193862 | D18: 191566 | E18: 173202 | F18: 179425 | G18: 218186 | H18: 234986 | I18: 281613 | J18: 320168 | K18: 300647 | L18: 346374 | M18: 415015 | N18: 414257 | O18: =O5*O26 -> 509036.58 | P18: =P5*P26 -> 589055.93 | Q18: =Q5*Q26 -> 621601.27 | R18: =R5*R26 -> 655944.74 | S18: =S5*S26 -> 677183.64
A19: Net Revenue (R$ thousand) | B19: 83077 | C19: 82043 | D19: 85019 | E19: 98902 | F19: 104375 | G19: 80496 | H19: 77154 | I19: 156269 | J19: 354810 | K19: 380070 | L19: 349283 | M19: 320811 | N19: 386901 | Y19: Yield Growth Assumption | Z19: 0.005
A20: Unit Price (R$ / Ton) | B20: 520 | C20: 420 | D20: 444 | E20: 571 | F20: 582 | G20: 369 | H20: 328 | I20: 555 | J20: 1108 | K20: 1264 | L20: 1008 | M20: 773 | N20: 934 | O20: =O9*O28 -> 907.76917 | P20: =P9*P28 -> 998.86149 | Q20: =Q9*Q28 -> 974.79022 | R20: =R9*R28 -> 1035.8347 | S20: =S9*S28 -> 1035.8347
A21: Total Cost (R$ thousand) | B21: -58920 | C21: -61891 | D21: -64080 | E21: -97913 | F21: -75483 | G21: -52980 | H21: -61257 | I21: -98128 | J21: -134769 | K21: -140849 | L21: -205003 | M21: -227896 | N21: -229100
A22: Unit Cost (R$ / Ton) | B22: -370 | C22: -320 | D22: -335 | E22: -565 | F22: -421 | G22: -243 | H22: -261 | I22: -348 | J22: -421 | K22: -468 | L22: -592 | M22: -549 | N22: -553 | O22: =(O20-O23)*-1 -> -644.71575 | P22: =(P20-P23)*-1 -> -709.41133 | Q22: =(Q20-Q23)*-1 -> -692.31543 | R22: =(R20-R23)*-1 -> -735.67044 | S22: =(S20-S23)*-1 -> -735.67044
A23: Unit Margin (R$ / Ton) | B23: 150 | C23: 100 | D23: 109 | E23: 6 | F23: 161 | G23: 126 | H23: 67 | I23: 207 | J23: 687 | K23: 796 | L23: 416 | M23: 224 | N23: 381 | O23: =O20*O24 -> 263.05342 | P23: =P20*P24 -> 289.45016 | Q23: =Q20*Q24 -> 282.47479 | R23: =R20*R24 -> 300.16426 | S23: =S20*S24 -> 300.16426
A24: Margin % | B24: =B23/B20 -> 0.28846154 | C24: =C23/C20 -> 0.23809524 | D24: =D23/D20 -> 0.2454955 | E24: =E23/E20 -> 0.010507881 | F24: =F23/F20 -> 0.2766323 | G24: =G23/G20 -> 0.34146341 | H24: =H23/H20 -> 0.20426829 | I24: =I23/I20 -> 0.37297297 | ... N24: =N23/N20 -> 0.40792291 | O24: =$B$25 -> 0.28978008 | P24: =$B$25 -> 0.28978008 | Q24: =$B$25 -> 0.28978008 | R24: =$B$25 -> 0.28978008 | S24: =$B$25 -> 0.28978008 | Y24: Future Contracts Implied Curve
A25: Margin Assumption | B25: =MEDIAN(B24:N24) -> 0.28978008 | Y25: Futures (05/12/26) (mm/dd/yy) | Z25: 2026 | AA25: 2027 | AB25: 2028 | AC25: 2029 | AD25: 2030
A26: Cottonseed tons/Cotton lint tons | B26: =B18/B5 -> 1.1635659 | C26: =C18/C5 -> 1.2687636 | D26: =D18/D5 -> 1.2110404 | E26: =E18/E5 -> 1.1669013 | F26: =F18/F5 -> 1.2713816 | G26: =G18/G5 -> 1.2859206 | H26: =H18/H5 -> 1.2676319 | I26: =I18/I5 -> 1.3039752 | ... N26: =N18/N5 -> 1.1216507 | O26: 1.2 | P26: 1.2 | Q26: 1.2 | R26: 1.2 | S26: 1.2
A27: Median | B27: =MEDIAN(B26:N26) -> 1.2506904 | Y27: Commodities
A28: Cottonseed Price/Cotton Lint Price | B28: =B20/B9 -> 0.12903226 | C28: =C20/C9 -> 0.098360656 | D28: =D20/D9 -> 0.10706535 | E28: =E20/E9 -> 0.11948106 | F28: =F20/F9 -> 0.10374332 | G28: =G20/G9 -> 0.064040264 | H28: =H20/H9 -> 0.052835052 | I28: =I20/I9 -> 0.092253989 | ... N28: =N20/N9 -> 0.097596656 | O28: =$B$29 -> 0.098360656 | P28: =$B$29 -> 0.098360656 | Q28: =$B$29 -> 0.098360656 | R28: =$B$29 -> 0.098360656 | S28: =$B$29 -> 0.098360656 | Y28: Cotton Lint ($/lb) | Z28: 0.8451 | AA28: 0.8593 | AB28: 0.7782 | AC28: 0.7668 | AD28: 0.7668
A29: Price/Cotton Lint Assumption | B29: =MEDIAN(B28:N28) -> 0.098360656 | Y29: Soybean ($/bu) | Z29: 12.18 | AA29: 12.13 | AB29: 11.67 | AC29: 11.47 | AD29: 11.47
Y30: Corn ($/bu) | Z30: 4.73 | AA30: 5.2025 | AB30: 5.2125 | AC30: 5.08 | AD30: 5.08
A31: Soybean Sold
A32: Quantity Sold (Ton) | B32: 394468 | C32: 537426 | D32: 634879 | E32: 539570 | F32: 746049 | G32: 842481 | H32: 898368 | I32: 899278 | J32: 1004595 | K32: 1274552 | L32: 1309363 | M32: 1013687 | N32: 1445837 | O32: ='Planted Area'!N6*AM7 -> 1602047.5 | P32: ='Planted Area'!O6*AN7 -> 1830133.8 | Q32: ='Planted Area'!P6*AO7 -> 1931248.6 | R32: ='Planted Area'!Q6*AP7 -> 2037950.1 | S32: ='Planted Area'!R6*AQ7 -> 2150546.9 | Y32: BRL/USD
A33: Net Revenue (R$ thousand) | B33: 328348 | C33: 478022 | D33: 634055 | E33: 583990 | F33: 720879 | G33: 875235 | H33: 1036218 | I33: 1291803 | J33: 1881516 | K33: 2973363 | L33: 3055726 | M33: 2092605 | N33: 2749065 | Y33: BRL/USD | Z33: 4.9535 | AA33: 5.3605 | AB33: 5.7765 | AC33: 6.2295 | AD33: 6.2295
A34: Hedhe Result (R$ thousand) | D34: -69398 | E34: 9682 | F34: 60340 | G34: -11041 | H34: -46758 | I34: -106204 | J34: -29291 | K34: 114114 | L34: 136600 | M34: 39624 | N34: 4394
A35: Hedge Adj. Net Revenue (R$ thousand) | D35: 564657 | E35: 593672 | F35: 781219 | G35: 864194 | H35: 989460 | I35: 1185599 | J35: 1852225 | K35: 3087477 | L35: 3192326 | M35: 2132229 | N35: 2753459 | Y35: Cotton Lint (brl/lb) | Z35: =Z28*Z$33 -> 4.1862028 | AA35: =AA28*AA$33 -> 4.6062777 | AB35: =AB28*AB$33 -> 4.4952723 | AC35: =AC28*AC$33 -> 4.7767806 | AD35: =AD28*AD$33 -> 4.7767806
A36: Unit Price (R$ / Ton) | B36: 830 | C36: 890 | D36: 889 | E36: 1100 | F36: 1047 | G36: 1026 | H36: 1101 | I36: 1318 | J36: 1844 | K36: 2422 | L36: 2438 | M36: 2103 | N36: 1904 | O36: =Z46 -> 2216.6576 | P36: =AA46 -> 2388.9401 | Q36: =AB46 -> 2476.7079 | R36: =AC46 -> 2625.1599 | S36: =AD46 -> 2625.1599 | Y36: Soybean (brl/bu) | Z36: =Z29*Z$33 -> 60.33363 | AA36: =AA29*AA$33 -> 65.022865 | AB36: =AB29*AB$33 -> 67.411755 | AC36: =AC29*AC$33 -> 71.452365 | AD36: =AD29*AD$33 -> 71.452365
A37: Total Cost (R$ thousand) | B37: -259742 | C37: -366835 | D37: -419781 | E37: -463229 | F37: -506506 | G37: -567844 | H37: -644331 | I37: -697641 | J37: -986071 | K37: -1449659 | L37: -1634559 | M37: -1599801 | N37: -1772371 | Y37: Corn (brl/bu) | Z37: =Z30*Z$33 -> 23.430055 | AA37: =AA30*AA$33 -> 27.888001 | AB37: =AB30*AB$33 -> 30.110006 | AC37: =AC30*AC$33 -> 31.64586 | AD37: =AD30*AD$33 -> 31.64586
A38: Unit Cost (R$ / Ton) | B38: -660 | C38: -680 | D38: -661 | E38: -859 | F38: -679 | G38: -674 | H38: -717 | I38: -776 | J38: -982 | K38: -1137 | L38: -1248 | M38: -1578 | N38: -1226 | O38: =(O36-O39)*-1 -> -1507.3271 | P38: =(P36-P39)*-1 -> -1624.4792 | Q38: =(Q36-Q39)*-1 -> -1684.1614 | R38: =(R36-R39)*-1 -> -1785.1087 | S38: =(S36-S39)*-1 -> -1785.1087
A39: Unit Margin (R$ / Ton) | B39: 170 | C39: 210 | D39: 228 | E39: 241 | F39: 368 | G39: 352 | H39: 384 | I39: 542 | J39: 862 | K39: 1285 | L39: 1190 | M39: 525 | N39: 678 | O39: =O36*O40 -> 709.33042 | P39: =P36*P40 -> 764.46082 | Q39: =Q36*Q40 -> 792.54652 | R39: =R36*R40 -> 840.05116 | S39: =S36*S40 -> 840.05116
A40: Margin % | B40: =B39/B36 -> 0.20481928 | C40: =C39/C36 -> 0.23595506 | D40: =D39/D36 -> 0.25646794 | E40: =E39/E36 -> 0.21909091 | F40: =F39/F36 -> 0.35148042 | G40: =G39/G36 -> 0.34307992 | H40: =H39/H36 -> 0.34877384 | I40: =I39/I36 -> 0.41122914 | ... N40: =N39/N36 -> 0.35609244 | O40: =$B$42 -> 0.32 | P40: =$B$42 -> 0.32 | Q40: =$B$42 -> 0.32 | R40: =$B$42 -> 0.32 | S40: =$B$42 -> 0.32 | Y40: lb/ton | Z40: 2204.62
A41: Median | B41: =MEDIAN(B40:N40) -> 0.34877384 | Y41: soybean bu/ton | Z41: 36.74
A42: Margin Assumption | B42: =32% -> 0.32 | Y42: corn bu/ton | Z42: 39.37
A44: Corn Sold | Y44: Expected Price
A45: Quantity Sold (Ton) | B45: 341161 | C45: 367671 | D45: 335695 | E45: 345691 | F45: 484912 | G45: 425900 | H45: 634644 | I45: 662840 | J45: 775925 | K45: 783768 | L45: 1071551 | M45: 658470 | N45: 1211592 | O45: ='Planted Area'!N8*AM9 -> 1219652.9 | P45: ='Planted Area'!O8*AN9 -> 1246518.4 | Q45: ='Planted Area'!P8*AO9 -> 1315388.5 | R45: ='Planted Area'!Q8*AP9 -> 1388063.7 | S45: ='Planted Area'!R8*AQ9 -> 1464754.2 | Y45: Cotton Lint (brl/ton) | Z45: =Z35*$Z40 -> 9228.9865 | AA45: =AA35*$Z40 -> 10155.092 | AB45: =AB35*$Z40 -> 9910.3672 | AC45: =AC35*$Z40 -> 10530.986 | AD45: =AD35*$Z40 -> 10530.986
A46: Net Revenue (R$ thousand) | B46: 99224 | C46: 111950 | D46: 121877 | E46: 164514 | F46: 152733 | G46: 146151 | H46: 253376 | I46: 383504 | J46: 527282 | K46: 710473 | L46: 846036 | M46: 523883 | N46: 1035234 | Y46: Soybean (brl/ton) | Z46: =Z36*$Z41 -> 2216.6576 | AA46: =AA36*$Z41 -> 2388.9401 | AB46: =AB36*$Z41 -> 2476.7079 | AC46: =AC36*$Z41 -> 2625.1599 | AD46: =AD36*$Z41 -> 2625.1599
A47: Hedhe Result (R$ thousand) | D47: -5258 | E47: 9171 | F47: 4809 | G47: -8757 | H47: -7833 | I47: -23165 | J47: -318 | K47: 39832 | L47: 118188 | M47: -13284 | N47: 27727 | Y47: Corn (brl/ton) | Z47: =Z37*$Z42 -> 922.44127 | AA47: =AA37*$Z42 -> 1097.9506 | AB47: =AB37*$Z42 -> 1185.4309 | AC47: =AC37*$Z42 -> 1245.8975 | AD47: =AD37*$Z42 -> 1245.8975
A48: Hedge Adj. Net Revenue (R$ thousand) | D48: 116619 | E48: 173685 | F48: 157542 | G48: 137394 | H48: 245543 | I48: 360339 | J48: 526964 | K48: 750305 | L48: 964224 | M48: 510599 | N48: 1062961
A49: Unit Price (R$ / Ton) | B49: 290 | C49: 300 | D49: 347 | E49: 502 | F49: 325 | G49: 323 | H49: 387 | I49: 544 | J49: 679 | K49: 957 | L49: 900 | M49: 775 | N49: 877 | O49: =Z47 -> 922.44127 | P49: =AA47 -> 1097.9506 | Q49: =AB47 -> 1185.4309 | R49: =AC47 -> 1245.8975 | S49: =AD47 -> 1245.8975
A50: Total Cost (R$ thousand) | B50: -90679 | C50: -90674 | D50: -81088 | E50: -106401 | F50: -128920 | G50: -133109 | H50: -198182 | I50: -230112 | J50: -428642 | K50: -542399 | L50: -693868 | M50: -424994 | N50: -678447
A51: Unit Cost (R$ / Ton) | B51: -270 | C51: -250 | D51: -242 | E51: -308 | F51: -266 | G51: -313 | H51: -312 | I51: -347 | J51: -552 | K51: -692 | L51: -648 | M51: -645 | N51: -560 | O51: =(O49-O52)*-1 -> -627.26006 | P51: =(P49-P52)*-1 -> -746.60641 | Q51: =(Q49-Q52)*-1 -> -806.09304 | R51: =(R49-R52)*-1 -> -847.21031 | S51: =(S49-S52)*-1 -> -847.21031
A52: Unit Margin (R$ / Ton) | B52: 20 | C52: 50 | D52: 106 | E52: 195 | F52: 59 | G52: 10 | H52: 75 | I52: 197 | J52: 127 | K52: 265 | L52: 252 | M52: 131 | N52: 317 | O52: =O49*O53 -> 295.1812 | P52: =P49*P53 -> 351.34419 | Q52: =Q49*Q53 -> 379.3379 | R52: =R49*R53 -> 398.6872 | S52: =S49*S53 -> 398.6872
A53: Margin % | B53: =B52/B49 -> 0.068965517 | C53: =C52/C49 -> 0.16666667 | D53: =D52/D49 -> 0.3054755 | E53: =E52/E49 -> 0.38844622 | F53: =F52/F49 -> 0.18153846 | G53: =G52/G49 -> 0.030959752 | H53: =H52/H49 -> 0.19379845 | I53: =I52/I49 -> 0.36213235 | ... N53: =N52/N49 -> 0.36145952 | O53: =$B$55 -> 0.32 | P53: =$B$55 -> 0.32 | Q53: =$B$55 -> 0.32 | R53: =$B$55 -> 0.32 | S53: =$B$55 -> 0.32
A54: Median | B54: =MEDIAN(B53:N53) -> 0.19379845
A55: Margin Assumption | B55: =0.32 -> 0.32
A59: Cattle Herd
A60: Quantity Sold (Heads) | B60: - | C60: - | D60: - | E60: - | F60: - | G60: - | H60: - | I60: 13000 | J60: 13285 | K60: 24318 | L60: 30295 | M60: 42621 | N60: 63480 | O60: ='Planted Area'!N9*O70 -> 50046 | P60: ='Planted Area'!O9*P70 -> 49247.007 | Q60: ='Planted Area'!P9*Q70 -> 51709.357 | R60: ='Planted Area'!Q9*R70 -> 54294.825 | S60: ='Planted Area'!R9*S70 -> 57009.566
A61: Net Revenue (R$ thousand) | B61: - | C61: - | D61: - | E61: - | F61: - | G61: - | H61: - | I61: 29528 | J61: 59377 | K61: 110862 | L61: 121007 | M61: 202280 | N61: 383851
A62: Hedhe Result (R$ thousand) | B62: - | C62: - | D62: - | E62: - | F62: - | G62: - | H62: - | I62: -3864 | J62: 1540 | K62: 1294 | L62: 15454 | M62: -3999 | N62: 6177
A63: Hedge Adj. Net Revenue (R$ thousand) | B63: - | C63: - | D63: - | E63: - | F63: - | G63: - | H63: - | I63: 25664 | J63: 60917 | K63: 112156 | L63: 136461 | M63: 198281 | N63: 390028
A64: Unit Price (R$ / Head) | B64: - | C64: - | D64: - | E64: - | F64: - | G64: - | H64: - | I64: 1974 | J64: 4585 | K64: 4612 | L64: 4504 | M64: 4652 | N64: 6144 | O64: 6144 | P64: 6144 | Q64: 6144 | R64: 6144 | S64: 6144
A65: Total Cost (R$ thousand) | B65: - | C65: - | D65: - | E65: - | F65: - | G65: - | H65: - | I65: -25027 | J65: -53800 | K65: -119413 | L65: -143966 | M65: -184773 | N65: -343489
A66: Unit Cost (R$ / Head) | B66: - | C66: - | D66: - | E66: - | F66: - | G66: - | H66: - | I66: -1925 | J66: -4050 | K66: -4910 | L66: -4752 | M66: -4335 | N66: -5411 | O66: -5411 | P66: -5411 | Q66: -5411 | R66: -5411 | S66: -5411
A67: Unit Margin (R$ / Head) | B67: - | C67: - | D67: - | E67: - | F67: - | G67: - | H67: - | I67: 49 | J67: 535 | K67: -298 | L67: -248 | M67: 317 | N67: 733 | O67: 733 | P67: 733 | Q67: 733 | R67: 733 | S67: 733
A68: Margin % | B68: - | C68: - | D68: - | E68: - | F68: - | G68: - | H68: - | I68: =I67/I64 -> 0.024822695 | J68: =J67/J64 -> 0.11668484 | K68: =K67/K64 -> -0.06461405 | L68: =L67/L64 -> -0.055062167 | M68: =M67/M64 -> 0.068142734 | N68: =N67/N64 -> 0.11930339 | O68: =O67/O64 -> 0.11930339 | P68: =P67/P64 -> 0.11930339 | ... S68: =S67/S64 -> 0.11930339
A70: Heads / ha | I70: =I60/'Planted Area'!I9 -> 3.6868973 | J70: =J60/'Planted Area'!J9 -> 2.6936334 | K70: =K60/'Planted Area'!K9 -> 6.1378092 | L70: =L60/'Planted Area'!L9 -> 5.7181955 | M70: =M60/'Planted Area'!M9 -> 7.6190561 | N70: =N60/'Planted Area'!N9 -> 7.6105982 | O70: =$B$72 -> 6 | P70: =$B$72 -> 6 | Q70: =$B$72 -> 6 | R70: =$B$72 -> 6 | S70: =$B$72 -> 6
A71: Median | B71: =MEDIAN(B70:N70) -> 5.9280024
A72: Heads / ha | B72: 6

Sheet CoE
A1: Debt
B2: 2013 | C2: 2014 | D2: 2015 | E2: 2016 | F2: 2017 | G2: 2018 | H2: 2019 | I2: 2020 | J2: 2021 | K2: 2022 | L2: 2023 | M2: 2024 | N2: 2025 | O2: 2026 | P2: 2027 | Q2: 2028 | R2: 2029 | S2: 2030
B3: A | C3: A | D3: A | E3: A | F3: A | G3: A | H3: A | I3: A | J3: A | K3: A | L3: A | M3: A | N3: A | O3: F | P3: F | Q3: F | R3: F | S3: F
A4: Loans and Financing | B4: ='Balance Sheet'!B53+'Balance Sheet'!B39 -> 1170289 | C4: ='Balance Sheet'!C53+'Balance Sheet'!C39 -> 1331976 | D4: ='Balance Sheet'!D53+'Balance Sheet'!D39 -> 1878877 | E4: ='Balance Sheet'!E53+'Balance Sheet'!E39 -> 1901245 | F4: ='Balance Sheet'!F53+'Balance Sheet'!F39 -> 1589174 | G4: ='Balance Sheet'!G53+'Balance Sheet'!G39 -> 1605071 | H4: ='Balance Sheet'!H53+'Balance Sheet'!H39 -> 1859766 | I4: ='Balance Sheet'!I53+'Balance Sheet'!I39 -> 2417283 | ... N4: ='Balance Sheet'!N53+'Balance Sheet'!N39 -> 7728284 | O4: =N4*(1+O5)+O15 -> 7728284 | P4: =O4*(1+P5)+P15 -> 7728284 | Q4: =P4*(1+Q5)+Q15 -> 7728284 | R4: =Q4*(1+R5)+R15 -> 7728284 | S4: =R4*(1+S5)+S15 -> 7728284
A5: ▲% | C5: =(C4-B4)/B4 -> 0.13815989 | D5: =(D4-C4)/C4 -> 0.41059373 | E5: =(E4-D4)/D4 -> 0.011904984 | F5: =(F4-E4)/E4 -> -0.16414034 | G5: =(G4-F4)/F4 -> 0.01000331 | H5: =(H4-G4)/G4 -> 0.15868145 | I5: =(I4-H4)/H4 -> 0.29977804 | J5: =(J4-I4)/I4 -> 0.070523807 | ... N5: =(N4-M4)/M4 -> 0.38044414
A6: Geomean | B6: {=GEOMEAN(C5:N5+1)-1} -> 0.17035019
A7: {='Income Statement'!A52:N52} -> Interest | B7: -36171 | C7: -68098 | D7: 35859 | E7: -194915 | F7: -94074 | G7: -77661 | H7: -101197 | I7: -53636 | J7: -98269 | K7: -459171 | L7: -454331 | M7: -517399 | N7: -827999 | O7: =N4*O8 -> -826926.39 | P7: =O4*P8 -> -826926.39 | Q7: =P4*Q8 -> -826926.39 | R7: =Q4*R8 -> -826926.39 | S7: =R4*S8 -> -826926.39
A8: % Rate | B8: =B7/B4 -> -0.03090775 | C8: =C7/C4 -> -0.051125546 | D8: =D7/D4 -> 0.019085337 | E8: =E7/E4 -> -0.10251966 | F8: =F7/F4 -> -0.05919679 | G8: =G7/G4 -> -0.048384776 | H8: =H7/H4 -> -0.054413835 | I8: =I7/I4 -> -0.022188548 | ... N8: =N7/N4 -> -0.10713879 | O8: =$B$10*-1 -> -0.107 | P8: =$B$10*-1 -> -0.107 | Q8: =$B$10*-1 -> -0.107 | R8: =$B$10*-1 -> -0.107 | S8: =$B$10*-1 -> -0.107
A10: Interest Rate | B10: 0.107
A12: Tax Rate | B12: ='Income Statement'!B65/'Income Statement'!B61*-1 -> 0.23076984 | C12: ='Income Statement'!C65/'Income Statement'!C61*-1 -> 0.21251586 | D12: ='Income Statement'!D65/'Income Statement'!D61*-1 -> 0.27291874 | E12: ='Income Statement'!E65/'Income Statement'!E61*-1 -> 4.7589522 | F12: ='Income Statement'!F65/'Income Statement'!F61*-1 -> 0.26293539 | G12: ='Income Statement'!G65/'Income Statement'!G61*-1 -> 0.3052227 | H12: ='Income Statement'!H65/'Income Statement'!H61*-1 -> 0.24024627 | I12: ='Income Statement'!I65/'Income Statement'!I61*-1 -> 0.25861313 | ... N12: ='Income Statement'!N65/'Income Statement'!N61*-1 -> 0.20802578
A13: Average tax rate | B13: =AVERAGE(B12:D12,F12:L12,N12) -> 0.25031248
A15: New Debt | O15: =IF(DCF!B22<0,DCF!B22*-1,0) -> 0 | P15: =IF(DCF!C22<0,DCF!C22*-1,0) -> 0 | Q15: =IF(DCF!D22<0,DCF!D22*-1,0) -> 0 | R15: =IF(DCF!E22<0,DCF!E22*-1,0) -> 0 | S15: =IF(DCF!F22<0,DCF!F22*-1,0) -> 0
A18: Risk Free (US 10y Treasury 2026) | B18: 0.04489
A19: Risk Premium (Damodaran) | B19: 0.0423
A20: EMBI+ Brazil | B20: 0.0228
A23: Debt Weight | B23: =1-B24 -> 0.35385027 | C23: =1-C24 -> 0.35757899 | D23: =1-D24 -> 0.43990059 | E23: =1-E24 -> 0.41968875 | F23: =1-F24 -> 0.37035041 | G23: =1-G24 -> 0.36479127 | H23: =1-H24 -> 0.38390802 | I23: =1-I24 -> 0.43410331 | ... S23: =1-S24 -> 0.52976332
A24: Equity Weight | B24: ='Balance Sheet'!B72/(B4+'Balance Sheet'!B72) -> 0.64614973 | C24: ='Balance Sheet'!C72/(C4+'Balance Sheet'!C72) -> 0.64242101 | D24: ='Balance Sheet'!D72/(D4+'Balance Sheet'!D72) -> 0.56009941 | E24: ='Balance Sheet'!E72/(E4+'Balance Sheet'!E72) -> 0.58031125 | F24: ='Balance Sheet'!F72/(F4+'Balance Sheet'!F72) -> 0.62964959 | G24: ='Balance Sheet'!G72/(G4+'Balance Sheet'!G72) -> 0.63520873 | H24: ='Balance Sheet'!H72/(H4+'Balance Sheet'!H72) -> 0.61609198 | I24: ='Balance Sheet'!I72/(I4+'Balance Sheet'!I72) -> 0.56589669 | ... S24: ='Balance Sheet'!S72/(S4+'Balance Sheet'!S72) -> 0.47023668
A27: Leveraged Beta | O27: =$B$28*(1+(1-'Income Statement'!$B$67)*(O23/O24)) -> 1.6217365 | P27: =$B$28*(1+(1-'Income Statement'!$B$67)*(P23/P24)) -> 1.5922641 | Q27: =$B$28*(1+(1-'Income Statement'!$B$67)*(Q23/Q24)) -> 1.561692 | R27: =$B$28*(1+(1-'Income Statement'!$B$67)*(R23/R24)) -> 1.5275302 | S27: =$B$28*(1+(1-'Income Statement'!$B$67)*(S23/S24)) -> 1.4944026
A28: Farming/Agriculture Damodaran Unleveraged Beta | B28: 0.81
A30: Cost of Equity | O30: =$B$18+O27*$B$19+$B$20 -> 0.13628945 | P30: =$B$18+P27*$B$19+$B$20 -> 0.13504277 | Q30: =$B$18+Q27*$B$19+$B$20 -> 0.13374957 | R30: =$B$18+R27*$B$19+$B$20 -> 0.13230453 | S30: =$B$18+S27*$B$19+$B$20 -> 0.13090323

Sheet Balance Sheet
A1: Balance Sheet
B2: 2013 | C2: 2014 | D2: 2015 | E2: 2016 | F2: 2017 | G2: 2018 | H2: 2019 | I2: 2020 | J2: 2021 | K2: 2022 | L2: 2023 | M2: 2024 | N2: 2025 | O2: 2026 | P2: 2027 | Q2: 2028 | R2: 2029 | S2: 2030
B3: A | C3: A | D3: A | E3: A | F3: A | G3: A | H3: A | I3: A | J3: A | K3: A | L3: A | M3: A | N3: A | O3: F | P3: F | Q3: F | R3: F | S3: F
A4: Cash and Cash Equivalents | B4: 392977 | C4: 371962 | D4: 701460 | E4: 1064506 | F4: 749328 | G4: 642736 | H4: 884769 | I4: 1604053 | J4: 139780 | K4: 1235775 | L4: 1613703 | M4: 1979575 | N4: 2647586
A5: Accounts Receivable | B5: 62438 | C5: 120663 | D5: 176691 | E5: 73392 | F5: 168128 | G5: 131546 | H5: 178405 | I5: 207283 | J5: 147414 | K5: 174291 | L5: 143694 | M5: 251157 | N5: 248085
A6: Advance to suppliers | B6: 2550 | C6: 5200 | D6: 4438 | E6: 1728 | F6: 9017 | G6: 8520 | H6: 2443 | I6: 3580 | J6: 29502 | K6: 14924 | L6: 9098 | M6: 30551 | N6: 35652
A7: Inventory | B7: 514819 | C7: 622101 | D7: 728192 | E7: 486425 | F7: 569524 | G7: 868522 | H7: 1071354 | I7: 1301082 | J7: 2806365 | K7: 3343980 | L7: 3656261 | M7: 3780562 | N7: 3722611
A8: Biological Assets | B8: 378481 | C8: 374372 | D8: 423705 | E8: 521174 | F8: 522997 | G8: 705390 | H8: 780589 | I8: 891804 | J8: 1690969 | K8: 1799576 | L8: 1488540 | M8: 1785392 | N8: 2350421
A9: Recoverable Taxes | B9: 78361 | C9: 98566 | D9: 89321 | E9: 66727 | F9: 45908 | G9: 86943 | H9: 41943 | I9: 39447 | J9: 126936 | K9: 139817 | L9: 127236 | M9: 207078 | N9: 290925
A10: Titles to be received | B10: 10313 | C10: 5474 | D10: 4444 | E10: 7948 | F10: 123657 | G10: 66342 | H10: 71657 | I10: 31207 | J10: 21919 | K10: 25852 | L10: 27590 | M10: 23176 | N10: 84366
A11: Operations with Derivatives | B11: 5278 | C11: 8936 | D11: 26639 | E11: 99963 | F11: 47140 | G11: 60222 | H11: 34008 | I11: 98587 | J11: 107676 | K11: 272728 | L11: 265314 | M11: 286904 | N11: 408226
A12: Other Accounts Receivable | B12: 4754 | C12: 3456 | D12: 15812 | E12: 2507 | F12: 3916 | G12: 5290 | H12: 11412 | I12: 6217 | J12: 23977 | K12: 15012 | L12: 19980 | M12: 15836 | N12: 8864
A13: Prepaid expenses | B13: 3793 | C13: 2712 | D13: 5469 | E13: 7721 | F13: 8354 | G13: 5060 | H13: 14030 | I13: 17141 | J13: 14275 | K13: 10183 | L13: 10982 | M13: 27245 | N13: 47153
A14: Others | B14: 0 | C14: 0 | D14: 677 | E14: 77 | F14: 2370 | G14: 1449 | H14: 189 | I14: 971 | J14: 573 | K14: 545 | L14: 3640 | M14: 2397 | N14: 1578
A16: Current Assets | B16: =SUM(B4:B14) -> 1453764 | C16: =SUM(C4:C14) -> 1613442 | D16: =SUM(D4:D14) -> 2176848 | E16: =SUM(E4:E14) -> 2332168 | F16: =SUM(F4:F14) -> 2250339 | G16: =SUM(G4:G14) -> 2582020 | H16: =SUM(H4:H14) -> 3090799 | I16: =SUM(I4:I14) -> 4201372 | ... N16: =SUM(N4:N14) -> 9845467
A18: Recoverable Taxes | B18: 20726 | C18: 31576 | D18: 51954 | E18: 55834 | F18: 62841 | G18: 82895 | H18: 122469 | I18: 111203 | J18: 152690 | K18: 204094 | L18: 233688 | M18: 269972 | N18: 397746
A19: Deferred Income Tax and social contribution | B19: 3924 | C19: 8358 | D19: 23509 | E19: 26265 | F19: 18760 | G19: 17168 | H19: 22517 | I19: 20480 | J19: 405662 | K19: 281819 | L19: 254080 | M19: 351448 | N19: 295230
A20: Operations with Derivatives | B20: 1938 | C20: 1329 | D20: 101852 | E20: 48648 | F20: 23766 | G20: 8770 | H20: 11328 | I20: 146785 | J20: 183607 | K20: 61677 | L20: 19746 | M20: 298888 | N20: 181721
A21: Advance to suppliers | B21: 68583 | C21: 71218 | D21: 76430 | E21: 71542 | F21: 57763 | G21: 46176 | H21: 30241 | I21: 59814 | J21: 74202 | K21: 79805 | L21: 75410 | M21: 30288 | N21: 32755
A22: Investments valued at fair value | B22: 0 | C22: 0 | D22: 0 | E22: 0 | F22: 0 | G22: 0 | H22: 650 | I22: 663 | J22: 684 | K22: 747 | L22: 1115 | M22: 1587 | N22: 1782
A23: Titles to be received | B23: 8594 | C23: 7956 | D23: 7464 | E23: 0 | F23: 0 | G23: 0 | H23: 5248 | I23: 2700 | J23: 26962 | K23: 31650 | L23: 0 | M23: 521 | N23: 107588
A24: Prepaid expenses | B24: 5796 | C24: 1665 | D24: 2830 | E24: 3777 | F24: 2567 | G24: 2659 | H24: 528 | I24: 437 | J24: 19 | K24: 458 | L24: 1798 | M24: 668 | N24: 10662
A25: Other credits | B25: 1684 | C25: 4760 | D25: 11991 | E25: 17309 | F25: 17029 | G25: 15643 | H25: 7945 | I25: 13705 | J25: 19770 | K25: 40174 | L25: 49656 | M25: 61078 | N25: 60094
A27: Non-Current Assets | B27: =SUM(B18:B25) -> 111245 | C27: =SUM(C18:C25) -> 126862 | D27: =SUM(D18:D25) -> 276030 | E27: =SUM(E18:E25) -> 223375 | F27: =SUM(F18:F25) -> 182726 | G27: =SUM(G18:G25) -> 173311 | H27: =SUM(H18:H25) -> 200926 | I27: =SUM(I18:I25) -> 355787 | ... N27: =SUM(N18:N25) -> 1087578
A29: Investment Property | B29: 4461 | C29: 5848 | D29: 93350 | E29: 210644 | F29: 202243 | G29: 209082 | H29: 0 | I29: 0 | J29: 333269 | K29: 385817 | L29: 430889 | M29: 58683 | N29: 53182
A30: Right of use Assets | B30: 0 | C30: 0 | D30: 0 | E30: 0 | F30: 0 | G30: 0 | H30: 555031 | I30: 828496 | J30: 3042185 | K30: 2881262 | L30: 2885337 | M30: 2567191 | N30: 2763422
A31: Fixed asset | B31: 2685343 | C31: 2747811 | D31: 2760438 | E31: 2683944 | F31: 2647977 | G31: 2784265 | H31: 3095999 | I31: 3168738 | J31: 3398063 | K31: 3733112 | L31: 4395692 | M31: 5417528 | N31: 7111885
A32: Intangible | B32: 6264 | C32: 4671 | D32: 2967 | E32: 3245 | F32: 10400 | G32: 6853 | H32: 15363 | I32: 35290 | J32: 118184 | K32: 131473 | L32: 137977 | M32: 121776 | N32: 473493
A34: Total Fixed Assets | B34: =SUM(B29:B32) -> 2696068 | C34: =SUM(C29:C32) -> 2758330 | D34: =SUM(D29:D32) -> 2856755 | E34: =SUM(E29:E32) -> 2897833 | F34: =SUM(F29:F32) -> 2860620 | G34: =SUM(G29:G32) -> 3000200 | H34: =SUM(H29:H32) -> 3666393 | I34: =SUM(I29:I32) -> 4032524 | ... N34: =SUM(N29:N32) -> 10401982
A36: Total Assets | B36: =SUM(B34,B27,B16) -> 4261077 | C36: =SUM(C34,C27,C16) -> 4498634 | D36: =SUM(D34,D27,D16) -> 5309633 | E36: =SUM(E34,E27,E16) -> 5453376 | F36: =SUM(F34,F27,F16) -> 5293685 | G36: =SUM(G34,G27,G16) -> 5755531 | H36: =SUM(H34,H27,H16) -> 6958118 | I36: =SUM(I34,I27,I16) -> 8589683 | ... N36: =SUM(N34,N27,N16) -> 21335027
A38: Suppliers | B38: 236217 | C38: 312759 | D38: 398860 | E38: 439735 | F38: 424041 | G38: 703564 | H38: 922000 | I38: 1101769 | J38: 1009194 | K38: 1564582 | L38: 1258175 | M38: 1888315 | N38: 2004563
A39: Loans and Financing | B39: 692418 | C39: 780739 | D39: 931732 | E39: 1155641 | F39: 860976 | G39: 738712 | H39: 699515 | I39: 377547 | J39: 669735 | K39: 1281537 | L39: 1413552 | M39: 1685130 | N39: 1591681
A40: Taxes and Contributions | B40: 18605 | C40: 13926 | D40: 6702 | E40: 7995 | F40: 28414 | G40: 24656 | H40: 57510 | I40: 57186 | J40: 57832 | K40: 207688 | L40: 109026 | M40: 17962 | N40: 153593
A41: Social and Labor Obligations | B41: 8875 | C41: 10344 | D41: 13763 | E41: 15308 | F41: 62701 | G41: 63007 | H41: 54572 | I41: 79989 | J41: 148613 | K41: 149756 | L41: 135279 | M41: 111208 | N41: 133955
A42: Advanced of customers | B42: 25029 | C42: 53200 | D42: 110401 | E42: 19285 | F42: 98652 | G42: 42163 | H42: 33289 | I42: 68264 | J42: 568043 | K42: 238942 | L42: 354070 | M42: 531616 | N42: 450508
A43: Operations with Derivatives | B43: 31433 | C43: 51651 | D43: 120544 | E43: 56604 | F43: 42583 | G43: 139866 | H43: 55230 | I43: 358969 | J43: 394582 | K43: 139585 | L43: 113012 | M43: 794133 | N43: 159003
A44: Securities Payable | B44: 126494 | C44: 49689 | D44: 75564 | E44: 81813 | F44: 17543 | G44: 11567 | H44: 12273 | I44: 12273 | J44: 93775 | K44: 86102 | L44: 53899 | M44: 612844 | N44: 590158
A45: Provisions of Taxes, Environmental and Labor Risks | B45: 16587 | C45: 17724 | D45: 20415 | E45: 15022 | F45: 2446 | G45: 2397 | H45: 4121 | I45: 5429 | J45: 32002 | K45: 38257 | L45: 13594 | M45: 13741 | N45: 3623
A46: Dividends to be paid | B46: 23923 | C46: 17758 | D46: 29100 | E46: 7112 | F46: 83598 | G46: 91804 | H46: 73759 | I46: 86332 | J46: 269803 | K46: 302370 | L46: 197404 | M46: 120857 | N46: 9441
A47: Leasing liabilities with third parties | B47: 0 | C47: 0 | D47: 0 | E47: 0 | F47: 0 | G47: 0 | H47: 114567 | I47: 162258 | J47: 511932 | K47: 523573 | L47: 298644 | M47: 248995 | N47: 249790
A48: Leasing to be Paid | B48: 13137 | C48: 28452 | D48: 34196 | E48: 37467 | F48: 37486 | G48: 58742 | H48: 225 | I48: 5283 | J48: 15048 | K48: 14146 | L48: 16762 | M48: 0 | N48: 0
A49: Other accounts to be paid | B49: 3028 | C49: 7044 | D49: 6693 | E49: 2394 | F49: 3792 | G49: 13560 | H49: 16375 | I49: 21680 | J49: 22338 | K49: 40670 | L49: 74361 | M49: 119982 | N49: 115523
A51: Current Liabilities | B51: =SUM(B38:B49) -> 1195746 | C51: =SUM(C38:C49) -> 1343286 | D51: =SUM(D38:D49) -> 1747970 | E51: =SUM(E38:E49) -> 1838376 | F51: =SUM(F38:F49) -> 1662232 | G51: =SUM(G38:G49) -> 1890038 | H51: =SUM(H38:H49) -> 2043436 | I51: =SUM(I38:I49) -> 2336979 | ... N51: =SUM(N38:N49) -> 5461838
A53: Loans and Financing | B53: 477871 | C53: 551237 | D53: 947145 | E53: 745604 | F53: 728198 | G53: 866359 | H53: 1160251 | I53: 2039736 | J53: 1918024 | K53: 2172734 | L53: 2979827 | M53: 3913274 | N53: 6136603
A54: Deferred Income Tax and Social Contributions | B54: 419813 | C54: 183511 | D54: 153309 | E54: 216085 | F54: 186975 | G54: 196247 | H54: 247531 | I54: 230802 | J54: 360906 | K54: 443717 | L54: 435872 | M54: 172793 | N54: 420140
A55: Operations with Derivatives | B55: 811 | C55: 10292 | D55: 31624 | E55: 24346 | F55: 14372 | G55: 7932 | H55: 5643 | I55: 58152 | J55: 139966 | K55: 20546 | L55: 21864 | M55: 415806 | N55: 190903
A56: Related party lease liability | B56: 0 | C56: 0 | D56: 0 | E56: 0 | F56: 0 | G56: 0 | H56: 0 | I56: 0 | J56: 0 | K56: 0 | L56: 0 | M56: 2099 | N56: 12457
A57: Securities Payable | B57: 29216 | C57: 16751 | D57: 36700 | E57: 0 | F57: 0 | G57: 0 | H57: 1412 | I57: 706 | J57: 14862 | K57: 14276 | L57: 154056 | N57: 207965
A58: Leasing liabilities with third parties | B58: 0 | C58: 0 | D58: 0 | E58: 0 | F58: 0 | G58: 0 | H58: 515149 | I58: 772026 | J58: 2824456 | K58: 2730474 | L58: 2977299 | M58: 2815335 | N58: 3151770
A59: Provisions for tax, environment, civil and labor risks | B59: 0 | C59: 0 | D59: 0 | E59: 0 | F59: 0 | G59: 0 | H59: 0 | I59: 0 | J59: 0 | K59: 0 | L59: 0 | M59: 0 | N59: 77136
A60: Other obligations | B60: 609 | C60: 549 | D60: 622 | E60: 79 | F60: 81 | G60: 55 | H60: 161 | I60: 114 | J60: 73 | K60: 520 | L60: 5217 | M60: 4988 | N60: 23173
A62: Non-Current Liabilities | B62: =SUM(B53:B60) -> 928320 | C62: =SUM(C53:C60) -> 762340 | D62: =SUM(D53:D60) -> 1169400 | E62: =SUM(E53:E60) -> 986114 | F62: =SUM(F53:F60) -> 929626 | G62: =SUM(G53:G60) -> 1070593 | H62: =SUM(H53:H60) -> 1930147 | I62: =SUM(I53:I60) -> 3101536 | ... N62: =SUM(N53:N60) -> 10220147
A64: Share capital | B64: 557434 | C64: 557434 | D64: 947522 | E64: 947522 | F64: 947522 | G64: 947522 | H64: 947522 | I64: 947522 | J64: 1512522 | K64: 1512522 | L64: 2012522 | M64: 2012522 | N64: 2926680
A65: Capital reserves | B65: 196902 | C65: 175360 | D65: 75056 | E65: 80984 | F65: 110566 | G65: 102704 | H65: 97760 | I65: 97504 | J65: 164953 | K65: 168544 | L65: 168704 | M65: -240778 | N65: 117357
A66: (-) Treasury Shares | B66: -7019 | C66: -32847 | D66: -32347 | E66: -30652 | F66: -60596 | G66: -36816 | H66: -64321 | I66: -52921 | J66: -116846 | K66: -280170 | L66: -57707 | M66: -48580 | N66: -31666
A67: Profit Reserves | B67: 397216 | C67: 484936 | D67: 291798 | E67: 292744 | F67: 404975 | G67: 496797 | H67: 680719 | I67: 978074 | J67: 1174813 | K67: 1891460 | L67: 1395452 | M67: 1591319 | N67: 710489
A68: Accumulated profits | B68: 0 | C68: 0 | D68: 0 | E68: 0 | F68: 1110732 | G68: 1087961 | H68: 0 | I68: 0 | J68: 0 | K68: 0 | L68: 0 | M68: 0 | N68: 0
A69: Other Comprehensive Results | B69: 857123 | C69: 985640 | D69: 891332 | E69: 1129785 | F69: 188628 | G69: 196585 | H69: 1122997 | I69: 970200 | J69: 789306 | K69: 1306441 | L69: 1408087 | M69: 683187 | N69: 1308243
A70: Non-controlling shareholders | B70: 128337 | C70: 189638 | D70: 186555 | E70: 177851 | F70: 0 | G70: 0 | H70: 199744 | I70: 210679 | J70: 251328 | K70: 297635 | L70: 314808 | M70: 106872 | N70: 624332
A72: Shareholders' Equity | B72: =B36-B51-B62 -> 2137011 | C72: =C36-C51-C62 -> 2393008 | D72: =D36-D51-D62 -> 2392263 | E72: =E36-E51-E62 -> 2628886 | F72: =F36-F51-F62 -> 2701827 | G72: =G36-G51-G62 -> 2794900 | H72: =H36-H51-H62 -> 2984535 | I72: =I36-I51-I62 -> 3151168 | ... N72: =N36-N51-N62 -> 5653042 | O72: =N72+O74 -> 5783813.5 | P72: =O72+P74 -> 6001722.8 | Q72: =P72+Q74 -> 6245819.5 | R72: =Q72+R74 -> 6543184.5 | S72: =R72+S74 -> 6859898.5
A73: ▲% | C73: =(C72-B72)/B72 -> 0.11979208 | D73: =(D72-C72)/C72 -> -0.00031132366 | E73: =(E72-D72)/D72 -> 0.098911784 | F73: =(F72-E72)/E72 -> 0.027745973 | G73: =(G72-F72)/F72 -> 0.034448172 | H73: =(H72-G72)/G72 -> 0.06785037 | I73: =(I72-H72)/H72 -> 0.055832148 | J73: =(J72-I72)/I72 -> 0.21018587 | ... S73: =(S72-R72)/R72 -> 0.048403662
A74: (1-Payout)*Net Income | O74: ='Income Statement'!O71*(1-O75) -> 130771.46 | P74: ='Income Statement'!P71*(1-P75) -> 217909.3 | Q74: ='Income Statement'!Q71*(1-Q75) -> 244096.7 | R74: ='Income Statement'!R71*(1-R75) -> 297365 | S74: ='Income Statement'!S71*(1-S75) -> 316714.09
A75: Payout Assumption | O75: 0.75 | P75: 0.75 | Q75: 0.75 | R75: 0.75 | S75: 0.75
A78: Total Liability | B78: =SUM(B72,B62,B51) -> 4261077 | C78: =SUM(C72,C62,C51) -> 4498634 | D78: =SUM(D72,D62,D51) -> 5309633 | E78: =SUM(E72,E62,E51) -> 5453376 | F78: =SUM(F72,F62,F51) -> 5293685 | G78: =SUM(G72,G62,G51) -> 5755531 | H78: =SUM(H72,H62,H51) -> 6958118 | I78: =SUM(I72,I62,I51) -> 8589683 | ... N78: =SUM(N72,N62,N51) -> 21335027
A79: Check | B79: =B36-B78 -> 0 | C79: =C36-C78 -> 0 | D79: =D36-D78 -> 0 | E79: =E36-E78 -> 0 | F79: =F36-F78 -> 0 | G79: =G36-G78 -> 0 | H79: =H36-H78 -> 0 | I79: =I36-I78 -> 0 | ... N79: =N36-N78 -> 0
A84: Working Capital
A85: Accounts Receivable | B85: =B5 -> 62438 | C85: =C5 -> 120663 | D85: =D5 -> 176691 | E85: =E5 -> 73392 | F85: =F5 -> 168128 | G85: =G5 -> 131546 | H85: =H5 -> 178405 | I85: =I5 -> 207283 | ... N85: =N5 -> 248085
A86: Advance to suppliers | B86: =B6 -> 2550 | C86: =C6 -> 5200 | D86: =D6 -> 4438 | E86: =E6 -> 1728 | F86: =F6 -> 9017 | G86: =G6 -> 8520 | H86: =H6 -> 2443 | I86: =I6 -> 3580 | ... N86: =N6 -> 35652
A87: Inventory | B87: =B7 -> 514819 | C87: =C7 -> 622101 | D87: =D7 -> 728192 | E87: =E7 -> 486425 | F87: =F7 -> 569524 | G87: =G7 -> 868522 | H87: =H7 -> 1071354 | I87: =I7 -> 1301082 | ... N87: =N7 -> 3722611
A88: Recoverable Taxes | B88: =B9 -> 78361 | C88: =C9 -> 98566 | D88: =D9 -> 89321 | E88: =E9 -> 66727 | F88: =F9 -> 45908 | G88: =G9 -> 86943 | H88: =H9 -> 41943 | I88: =I9 -> 39447 | ... N88: =N9 -> 290925
A89: Titles to be received | B89: =B10 -> 10313 | C89: =C10 -> 5474 | D89: =D10 -> 4444 | E89: =E10 -> 7948 | F89: =F10 -> 123657 | G89: =G10 -> 66342 | H89: =H10 -> 71657 | I89: =I10 -> 31207 | ... N89: =N10 -> 84366
A90: Other Accounts Receivable | B90: =B12 -> 4754 | C90: =C12 -> 3456 | D90: =D12 -> 15812 | E90: =E12 -> 2507 | F90: =F12 -> 3916 | G90: =G12 -> 5290 | H90: =H12 -> 11412 | I90: =I12 -> 6217 | ... N90: =N12 -> 8864
A91: Prepaid expenses | B91: =B13 -> 3793 | C91: =C13 -> 2712 | D91: =D13 -> 5469 | E91: =E13 -> 7721 | F91: =F13 -> 8354 | G91: =G13 -> 5060 | H91: =H13 -> 14030 | I91: =I13 -> 17141 | ... N91: =N13 -> 47153
A92: Assets | B92: =SUM(B85:B91) -> 677028 | C92: =SUM(C85:C91) -> 858172 | D92: =SUM(D85:D91) -> 1024367 | E92: =SUM(E85:E91) -> 646448 | F92: =SUM(F85:F91) -> 928504 | G92: =SUM(G85:G91) -> 1172223 | H92: =SUM(H85:H91) -> 1391244 | I92: =SUM(I85:I91) -> 1605957 | ... N92: =SUM(N85:N91) -> 4437656
A95: Suppliers | B95: =B38 -> 236217 | C95: =C38 -> 312759 | D95: =D38 -> 398860 | E95: =E38 -> 439735 | F95: =F38 -> 424041 | G95: =G38 -> 703564 | H95: =H38 -> 922000 | I95: =I38 -> 1101769 | ... N95: =N38 -> 2004563
A96: Taxes and Contributions | B96: =B40 -> 18605 | C96: =C40 -> 13926 | D96: =D40 -> 6702 | E96: =E40 -> 7995 | F96: =F40 -> 28414 | G96: =G40 -> 24656 | H96: =H40 -> 57510 | I96: =I40 -> 57186 | ... N96: =N40 -> 153593
A97: Social and Labor Obligations | B97: =B41 -> 8875 | C97: =C41 -> 10344 | D97: =D41 -> 13763 | E97: =E41 -> 15308 | F97: =F41 -> 62701 | G97: =G41 -> 63007 | H97: =H41 -> 54572 | I97: =I41 -> 79989 | ... N97: =N41 -> 133955
A98: Advanced of customers | B98: =B42 -> 25029 | C98: =C42 -> 53200 | D98: =D42 -> 110401 | E98: =E42 -> 19285 | F98: =F42 -> 98652 | G98: =G42 -> 42163 | H98: =H42 -> 33289 | I98: =I42 -> 68264 | ... N98: =N42 -> 450508
A99: Liabilities | B99: =SUM(B95:B98) -> 288726 | C99: =SUM(C95:C98) -> 390229 | D99: =SUM(D95:D98) -> 529726 | E99: =SUM(E95:E98) -> 482323 | F99: =SUM(F95:F98) -> 613808 | G99: =SUM(G95:G98) -> 833390 | H99: =SUM(H95:H98) -> 1067371 | I99: =SUM(I95:I98) -> 1307208 | ... N99: =SUM(N95:N98) -> 2742619
A101: Working Capital | B101: =B92-B99 -> 388302 | C101: =C92-C99 -> 467943 | D101: =D92-D99 -> 494641 | E101: =E92-E99 -> 164125 | F101: =F92-F99 -> 314696 | G101: =G92-G99 -> 338833 | H101: =H92-H99 -> 323873 | I101: =I92-I99 -> 298749 | ... N101: =N92-N99 -> 1695037
A102: =_xlfn.UNICHAR(916) -> Δ | C102: =(C101-B101) -> 79641 | D102: =(D101-C101) -> 26698 | E102: =(E101-D101) -> -330516 | F102: =(F101-E101) -> 150571 | G102: =(G101-F101) -> 24137 | H102: =(H101-G101) -> -14960 | I102: =(I101-H101) -> -25124 | J102: =(J101-I101) -> 1087957 | ... N102: =(N101-M101) -> -91467
A103: % of Revenue Ex | C103: =C102/'Income Statement'!C18 -> 0.059611348 | D103: =D102/'Income Statement'!D18 -> 0.018017872 | E103: =E102/'Income Statement'!E18 -> -0.20632169 | F103: =F102/'Income Statement'!F18 -> 0.081036934 | G103: =G102/'Income Statement'!G18 -> 0.011498316 | H103: =H102/'Income Statement'!H18 -> -0.0058992746 | I103: =I102/'Income Statement'!I18 -> -0.0081109342 | J103: =J102/'Income Statement'!J18 -> 0.24934784 | ... N103: =N102/'Income Statement'!N18 -> -0.010693959
A104: Geomean | B104: {=GEOMEAN(C103:N103+1)-1} -> 0.015098274

Sheet ▲ PPE
A1: (R$ thud) | B1: Category | C1: Opening Balance | D1: Business Combinations | E1: Additions | F1: Disposals | G1: Transfers | H1: Reclassifications | I1: Fair Value Realization | J1: Depreciation | K1: Closing Balance | O1: Capex | P1: 2013 | Q1: 2014 | R1: 2015 | S1: 2016 | T1: 2017 | U1: 2018 | V1: 2019 | W1: 2020 | X1: 2021 | Y1: 2022 | Z1: 2023 | AA1: 2024 | AB1: 2025 | AC1: 2026 | AD1: 2027 | AE1: 2028 | AF1: 2029 | AG1: 2030
A2: 2025 | B2: Farmland | C2: 2466270 | D2: - | E2: 842051 | F2: - | G2: -9000 | H2: 16179 | I2: - | J2: - | K2: =SUM(C2:J2) -> 3315500 | O2: Farmland | P2: {=_xlfn._xlws.FILTER($E:$E,$A:$A=P1)} -> 53468 | Q2: {=_xlfn._xlws.FILTER($E:$E,$A:$A=Q1)} -> 1321 | R2: {=_xlfn._xlws.FILTER($E:$E,$A:$A=R1)} -> 85579 | S2: {=_xlfn._xlws.FILTER($E:$E,$A:$A=S1)} -> 2 | T2: {=_xlfn._xlws.FILTER($E:$E,$A:$A=T1)} -> 4400 | U2: {=_xlfn._xlws.FILTER($E:$E,$A:$A=U1)} -> 2005 | V2: {=_xlfn._xlws.FILTER($E:$E,$A:$A=V1)} -> 3070 | W2: {=_xlfn._xlws.FILTER($E:$E,$A:$A=W1)} -> 102 | ... AB2: {=_xlfn._xlws.FILTER($E:$E,$A:$A=AB1)} -> 842051
A3: 2025 | B3: Soil Improvement and Development | C3: 790417 | D3: 117615 | E3: 305163 | F3: -6314 | G3: 475 | H3: - | I3: 62 | J3: -155305 | K3: =SUM(C3:J3) -> 1052113 | O3: Soil Improvement and Development | P3: 64018 | Q3: 76203 | R3: 35514 | S3: 26439 | T3: 32027 | U3: 48225 | V3: 46403 | W3: 76166 | X3: 153372 | Y3: 187328 | Z3: 197866 | AA3: 288411 | AB3: 305163
A4: 2025 | B4: Buildings and Improvements | C4: 632288 | D4: 60973 | E4: 966 | F4: -71 | G4: 142569 | H4: 81 | I4: -18 | J4: -39493 | K4: =SUM(C4:J4) -> 797295 | O4: Buildings and Improvements | P4: 475 | Q4: 680 | R4: 201 | S4: 104 | T4: 1779 | U4: 2931 | V4: 1931 | W4: 1373 | X4: 1060 | Y4: 2442 | Z4: 34878 | AA4: 1609 | AB4: 966
A5: 2025 | B5: Agricultural Equipment and Industrial Facilities | C5: 1048834 | D5: 148888 | E5: 209512 | F5: -10620 | G5: 150853 | H5: 861 | I5: -13779 | J5: -124902 | K5: =SUM(C5:J5) -> 1409647 | O5: Agricultural Equipment and Industrial Facilities | P5: 80753 | Q5: 51291 | R5: 32761 | S5: 25879 | T5: 37060 | U5: 114969 | V5: 106099 | W5: 89666 | X5: 171752 | Y5: 230228 | Z5: 133736 | AA5: 168570 | AB5: 209512
A6: 2025 | B6: Vehicles | C6: 117575 | D6: 14700 | E6: 3850 | F6: -350 | G6: 239 | H6: - | I6: -1691 | J6: -10486 | K6: =SUM(C6:J6) -> 123837 | O6: Vehicles | P6: 7508 | Q6: 3456 | R6: 2912 | S6: 1026 | T6: 3440 | U6: 19315 | V6: 11554 | W6: 2636 | X6: 3471 | Y6: 4797 | Z6: 7419 | AA6: 96127 | AB6: 3850
A7: 2025 | B7: Furniture and Fixtures | C7: 25855 | D7: 720 | E7: 6164 | F7: -246 | G7: 579 | H7: 45 | I7: -100 | J7: -3917 | K7: =SUM(C7:J7) -> 29100 | O7: Furniture and Fixtures | P7: 991 | Q7: 1062 | R7: 902 | S7: 1484 | T7: 987 | U7: 2601 | V7: 2149 | W7: 3033 | X7: 3016 | Y7: 4710 | Z7: 6884 | AA7: 7810 | AB7: 6164
A8: 2025 | B8: Office Equipment and Installations | C8: 41139 | D8: -942 | E8: 8681 | F8: -262 | G8: 877 | H8: 30 | I8: - | J8: -13652 | K8: =SUM(C8:J8) -> 35871 | O8: Office Equipment and Installations | P8: 1672 | Q8: 2364 | R8: 1537 | S8: 1199 | T8: 1907 | U8: 4632 | V8: 6581 | W8: 8863 | X8: 16259 | Y8: 13201 | Z8: 15553 | AA8: 12283 | AB8: 8681
A9: 2025 | B9: Other | C9: 14950 | D9: 81 | E9: 4839 | F9: -78 | G9: 474 | H9: -1464 | I9: - | J9: -290 | K9: =SUM(C9:J9) -> 18512 | O9: Other | P9: 373 | Q9: 358 | R9: 233 | S9: 149 | T9: 213 | U9: 593 | V9: 890 | W9: 763 | X9: 594 | Y9: 910 | Z9: 1116 | AA9: 2637 | AB9: 4839
A10: 2025 | B10: Advances to Suppliers | O10: Advances to Suppliers | P10: 16677 | Q10: 3252 | R10: - | S10: 0 | T10: 0 | U10: 0 | V10: 0 | W10: 0 | X10: 0 | Y10: 0 | Z10: 0 | AA10: 0 | AB10: 0
A11: 2025 | B11: Construction in Progress | C11: 280200 | E11: 348998 | F11: - | G11: -287066 | H11: -12122 | I11: - | J11: - | K11: =SUM(C11:J11) -> 330010 | O11: Construction in Progress | P11: 36808 | Q11: 55479 | R11: 39378 | S11: 19725 | T11: 48641 | U11: 72483 | V11: 86519 | W11: 27170 | X11: 75039 | Y11: 142892 | Z11: 245249 | AA11: 463647 | AB11: 348998
A12: 2025 | B12: Bearer Plants | O12: Bearer Plants | P12: 0 | Q12: 0 | R12: - | S12: - | T12: - | U12: - | V12: - | W12: 0 | X12: 0 | Y12: 0 | Z12: 0 | AA12: 0 | AB12: 0
A13: 2025 | B13: Total | C13: =SUM(C2:C11) -> 5417528 | D13: =SUM(D2:D11) -> 342035 | E13: =SUM(E2:E11) -> 1730224 | F13: =SUM(F2:F11) -> -17941 | G13: =SUM(G2:G11) -> 0 | H13: =SUM(H2:H11) -> 3610 | I13: =SUM(I2:I11) -> -15526 | J13: =SUM(J2:J11) -> -348045 | K13: =SUM(K2:K11) -> 7111885 | O13: Total | P13: 262743 | Q13: 195466 | R13: 199017 | S13: 76007 | T13: 130454 | U13: 267754 | V13: 265196 | W13: 209772 | X13: 424884 | Y13: 586693 | Z13: 1008406 | AA13: 1092004 | AB13: 1730224
O14: =_xlfn.UNICHAR(916) -> Δ | Q14: =(Q13-P13)/P13 -> -0.2560563 | R14: =(R13-Q13)/Q13 -> 0.018166842 | S14: =(S13-R13)/R13 -> -0.6180879 | T14: =(T13-S13)/S13 -> 0.71634192 | U14: =(U13-T13)/T13 -> 1.0524783 | V14: =(V13-U13)/U13 -> -0.0095535454 | W14: =(W13-V13)/V13 -> -0.20899259 | X14: =(X13-W13)/W13 -> 1.0254562 | ... AB14: =(AB13-AA13)/AA13 -> 0.58444841
A15: 2024 | B15: Farmland | C15: 2083280 | E15: 50910 | F15: -37844 | G15: 3209 | H15: 366715 | I15: - | J15: - | K15: =SUM(C15:J15) -> 2466270
A16: 2024 | B16: Soil Improvement and Development | C16: 613121 | E16: 288411 | F16: - | G16: -1864 | H16: 12191 | I16: - | J16: -121442 | K16: =SUM(C16:J16) -> 790417 | O16: Initial PPE | P16: {=_xlfn._xlws.FILTER($C:$C,($A:$A=P$1)*($B:$B="Total"))} -> 2594571 | Q16: {=_xlfn._xlws.FILTER($C:$C,($A:$A=Q$1)*($B:$B="Total"))} -> 2685343 | R16: {=_xlfn._xlws.FILTER($C:$C,($A:$A=R$1)*($B:$B="Total"))} -> 2753659 | S16: {=_xlfn._xlws.FILTER($C:$C,($A:$A=S$1)*($B:$B="Total"))} -> 2764677 | T16: {=_xlfn._xlws.FILTER($C:$C,($A:$A=T$1)*($B:$B="Total"))} -> 2686064 | U16: {=_xlfn._xlws.FILTER($C:$C,($A:$A=U$1)*($B:$B="Total"))} -> 2647977 | V16: {=_xlfn._xlws.FILTER($C:$C,($A:$A=V$1)*($B:$B="Total"))} -> 2784265 | W16: {=_xlfn._xlws.FILTER($C:$C,($A:$A=W$1)*($B:$B="Total"))} -> 2878989 | ... AB16: {=_xlfn._xlws.FILTER($C:$C,($A:$A=AB$1)*($B:$B="Total"))} -> 5417528
A17: 2024 | B17: Buildings and Improvements | C17: 533164 | E17: 1609 | F17: -150 | G17: 122009 | H17: 6549 | I17: - | J17: -30893 | K17: =SUM(C17:J17) -> 632288 | O17: Ending PPE | P17: {=_xlfn._xlws.FILTER($K:$K,($A:$A=P$1)*($B:$B="Total"))} -> 2685343 | Q17: {=_xlfn._xlws.FILTER($K:$K,($A:$A=Q$1)*($B:$B="Total"))} -> 2747811 | R17: {=_xlfn._xlws.FILTER($K:$K,($A:$A=R$1)*($B:$B="Total"))} -> 2764677 | S17: {=_xlfn._xlws.FILTER($K:$K,($A:$A=S$1)*($B:$B="Total"))} -> 2686064 | T17: {=_xlfn._xlws.FILTER($K:$K,($A:$A=T$1)*($B:$B="Total"))} -> 2647977 | U17: {=_xlfn._xlws.FILTER($K:$K,($A:$A=U$1)*($B:$B="Total"))} -> 2784265 | V17: {=_xlfn._xlws.FILTER($K:$K,($A:$A=V$1)*($B:$B="Total"))} -> 2878993 | W17: {=_xlfn._xlws.FILTER($K:$K,($A:$A=W$1)*($B:$B="Total"))} -> 2944444 | ... AB17: {=_xlfn._xlws.FILTER($K:$K,($A:$A=AB$1)*($B:$B="Total"))} -> 7111885
A18: 2024 | B18: Agricultural Equipment and Industrial Facilities | C18: 862913 | E18: 168570 | F18: -13851 | G18: 181295 | H18: -1623 | I18: -17173 | J18: -131297 | K18: =SUM(C18:J18) -> 1048834 | O18: =_xlfn.UNICHAR(916)&"% Ending PPE" -> Δ% Ending PPE | P18: =(P17-P16)/P16 -> 0.03498536 | Q18: =(Q17-P17)/P17 -> 0.023262578 | R18: =(R17-Q17)/Q17 -> 0.0061379767 | S18: =(S17-R17)/R17 -> -0.028434786 | T18: =(T17-S17)/S17 -> -0.014179483 | U18: =(U17-T17)/T17 -> 0.051468725 | V18: =(V17-U17)/U17 -> 0.034022624 | W18: =(W17-V17)/V17 -> 0.022733991 | X18: =(X17-W17)/W17 -> 0.15405931 | ... AB18: =(AB17-AA17)/AA17 -> 0.31275464
A19: 2024 | B19: Vehicles | C19: 104587 | E19: 96127 | F19: -71221 | G19: 804 | H19: -114 | I19: -2683 | J19: -9925 | K19: =SUM(C19:J19) -> 117575
A20: 2024 | B20: Furniture and Fixtures | C20: 20224 | E20: 7810 | F20: -207 | G20: 1325 | H20: - | I20: -162 | J20: -3135 | K20: =SUM(C20:J20) -> 25855
A21: 2024 | B21: Office Equipment and Installations | C21: 41837 | E21: 12283 | F21: -469 | G21: 336 | H21: 122 | I21: - | J21: -12970 | K21: =SUM(C21:J21) -> 41139 | O21: Depreciation | P21: 2013 | Q21: 2014 | R21: 2015 | S21: 2016 | T21: 2017 | U21: 2018 | V21: 2019 | W21: 2020 | X21: 2021 | Y21: 2022 | Z21: 2023 | AA21: 2024 | AB21: 2025
A22: 2024 | B22: Other | C22: 10278 | E22: 2637 | F22: -8 | G22: 2573 | H22: -393 | I22: - | J22: -137 | K22: =SUM(C22:J22) -> 14950 | O22: Farmland | P22: {=_xlfn._xlws.FILTER($J:$J,$A:$A=P21)} -> - | Q22: {=_xlfn._xlws.FILTER($J:$J,$A:$A=Q21)} -> - | R22: {=_xlfn._xlws.FILTER($J:$J,$A:$A=R21)} -> - | S22: {=_xlfn._xlws.FILTER($J:$J,$A:$A=S21)} -> - | T22: {=_xlfn._xlws.FILTER($J:$J,$A:$A=T21)} -> - | U22: {=_xlfn._xlws.FILTER($J:$J,$A:$A=U21)} -> - | V22: {=_xlfn._xlws.FILTER($J:$J,$A:$A=V21)} -> - | W22: {=_xlfn._xlws.FILTER($J:$J,$A:$A=W21)} -> 0 | ... AB22: {=_xlfn._xlws.FILTER($J:$J,$A:$A=AB21)} -> -
A23: 2024 | B23: Advances to Suppliers | O23: Soil Improvement and Development | P23: -47762 | Q23: -34476 | R23: -35167 | S23: -30710 | T23: -28939 | U23: -28760 | V23: -28263 | W23: -34160 | X23: -48698 | Y23: -71664 | Z23: -98573 | AA23: -121442 | AB23: -155305
A24: 2024 | B24: Construction in Progress | C24: 126288 | E24: 463647 | F24: - | G24: -309687 | H24: -48 | I24: - | J24: - | K24: =SUM(C24:J24) -> 280200 | O24: Buildings and Improvements | P24: -5134 | Q24: -6742 | R24: -7610 | S24: -8334 | T24: -9829 | U24: -15722 | V24: -17483 | W24: -20186 | X24: -21281 | Y24: -22175 | Z24: -29279 | AA24: -30893 | AB24: -39493
A25: 2024 | B25: Bearer Plants | O25: Agricultural Equipment and Industrial Facilities | P25: -46801 | Q25: -56037 | R25: -54222 | S25: -50810 | T25: -48466 | U25: -64156 | V25: -61294 | W25: -68329 | X25: -90465 | Y25: -105667 | Z25: -123594 | AA25: -131297 | AB25: -124902
A26: 2024 | B26: Total | C26: 4395692 | E26: 1092004 | F26: -123.75 | G26: - | H26: 383.399 | I26: -20.018 | J26: -309799 | K26: =SUM(K15:K24) -> 5417528 | O26: Vehicles | P26: -1877 | Q26: -2333 | R26: -2264 | S26: -3119 | T26: -2260 | U26: -4240 | V26: -5820 | W26: -5609 | X26: -8409 | Y26: -6715 | Z26: -9080 | AA26: -9925 | AB26: -10486
O27: Furniture and Fixtures | P27: -900 | Q27: -784 | R27: -800 | S27: -838 | T27: -983 | U27: -1120 | V27: -1216 | W27: -1411 | X27: -1887 | Y27: -2203 | Z27: -2582 | AA27: -3135 | AB27: -3917
A28: 2023 | B28: Farmland | C28: 1717425 | E28: 365705 | F28: - | G28: 150 | H28: - | I28: - | J28: - | K28: 2083280 | O28: Office Equipment and Installations | P28: -795 | Q28: -1275 | R28: -1546 | S28: -1534 | T28: -1626 | U28: -2067 | V28: -2515 | W28: -3618 | X28: -6156 | Y28: -8529 | Z28: -11168 | AA28: -12970 | AB28: -13652
A29: 2023 | B29: Soil Improvement and Development | C29: 513509 | E29: 197866 | F29: -344 | G29: 663 | H29: - | I29: - | J29: -98573 | K29: 613121 | O29: Other | P29: - | Q29: - | R29: - | S29: -114 | T29: - | U29: -5 | V29: -4 | W29: -35 | X29: -85 | Y29: -120 | Z29: -124 | AA29: -137 | AB29: -290
A30: 2023 | B30: Buildings and Improvements | C30: 446759 | E30: 34878 | F30: -3366 | G30: 85550 | H30: - | I30: -1378 | J30: -29279 | K30: 533164 | O30: Advances to Suppliers | P30: - | Q30: - | R30: - | S30: 0 | T30: 0 | U30: 0 | V30: 0 | W30: 0 | X30: 0 | Y30: 0 | Z30: 0 | AA30: 0 | AB30: 0
A31: 2023 | B31: Agricultural Equipment and Industrial Facilities | C31: 844123 | E31: 133736 | F31: -7991 | G31: 38419 | H31: -3404 | I31: -18376 | J31: -123594 | K31: 862913 | O31: Construction in Progress | P31: - | Q31: - | R31: - | S31: - | T31: - | U31: - | V31: - | W31: 0 | X31: - | Y31: - | Z31: - | AA31: - | AB31: -
A32: 2023 | B32: Vehicles | C32: 59710 | E32: 7419 | F32: -21802 | G32: 71842 | H32: 444 | I32: -3946 | J32: -9080 | K32: 104587 | O32: Bearer Plants | P32: 0 | Q32: 0 | R32: - | S32: -2119 | T32: -1414 | U32: -706 | V32: - | W32: 0 | X32: 0 | Y32: 0 | Z32: 0 | AA32: 0 | AB32: 0
A33: 2023 | B33: Furniture and Fixtures | C33: 16110 | E33: 6884 | F33: -484 | G33: 551 | H33: -9 | I33: -246 | J33: -2582 | K33: 20224 | O33: Total | P33: -103269 | Q33: -101647 | R33: -101609 | S33: -97578 | T33: -93517 | U33: -116776 | V33: -116595 | W33: -133348 | X33: -176981 | Y33: -217073 | Z33: -274400 | AA33: -309799 | AB33: -348045 | AC33: =AC34*AB106 -> 426713.1 | AD33: =AD34*AC106 -> 445012.98 | AE33: =AE34*AD106 -> 464409.99 | AF33: =AF34*AE106 -> 484948.08 | AG33: =AG34*AF106 -> 506674.02
A34: 2023 | B34: Office Equipment and Installations | C34: 35796 | E34: 15553 | F34: -316 | G34: 1988 | H34: 2 | I34: -18 | J34: -11168 | K34: 41837 | O34: % of initial PPE | AC34: =DCF!B18 -> 0.06 | AD34: =DCF!C18 -> 0.06 | AE34: =DCF!D18 -> 0.06 | AF34: =DCF!E18 -> 0.06 | AG34: =DCF!F18 -> 0.06
A35: 2023 | B35: Other | C35: 9354 | E35: 1116 | F35: - | G35: 225 | H35: -293 | I35: - | J35: -124 | K35: 10278
A36: 2023 | B36: Advances to Suppliers | O36: Capex % of Initial Total PPE
A37: 2023 | B37: Construction in Progress | C37: 90326 | E37: 245249 | F37: - | G37: -199388 | H37: -9899 | I37: - | J37: - | K37: 126288 | O37: Farmland | P37: =P2/P$16 -> 0.020607646 | Q37: =Q2/Q$16 -> 0.00049192971 | R37: =R2/R$16 -> 0.031078285 | S37: =S2/S$16 -> 7.2341181e-07 | T37: =T2/T$16 -> 0.0016380846 | U37: =U2/U$16 -> 0.0007571818 | V37: =V2/V$16 -> 0.0011026249 | W37: =W2/W$16 -> 3.5429104e-05 | X37: 0 | Y37: =Y2/Y$16 -> 5.4442781e-05 | Z37: =Z2/Z$16 -> 0.097962504 | AA37: =AA2/AA$16 -> 0.011581794 | AB37: =AB2/AB$16 -> 0.15543085
A38: 2023 | B38: Bearer Plants | O38: Soil Improvement and Development | P38: =P3/P$16 -> 0.024673829 | Q38: =Q3/Q$16 -> 0.02837738 | R38: =R3/R$16 -> 0.012897022 | S38: =S3/S$16 -> 0.0095631425 | T38: =T3/T$16 -> 0.011923394 | U38: =U3/U$16 -> 0.018212016 | V38: =V3/V$16 -> 0.016666158 | W38: =W3/W$16 -> 0.026455815 | X38: 0 | Y38: =Y3/Y$16 -> 0.055127877 | Z38: =Z3/Z$16 -> 0.053002964 | AA38: =AA3/AA$16 -> 0.065612195 | AB38: =AB3/AB$16 -> 0.056328827
A39: 2023 | B39: Total | C39: =SUM(C28:C37) -> 3733112 | D39: =SUM(D28:D37) -> 0 | E39: =SUM(E28:E37) -> 1008406 | F39: =SUM(F28:F37) -> -34303 | G39: =SUM(G28:G37) -> 0 | H39: =SUM(H28:H37) -> -13159 | I39: =SUM(I28:I37) -> -23964 | J39: =SUM(J28:J37) -> -274400 | K39: =SUM(K28:K37) -> 4395692 | O39: Buildings and Improvements | P39: =P4/P$16 -> 0.00018307458 | Q39: =Q4/Q$16 -> 0.0002532265 | R39: =R4/R$16 -> 7.2993788e-05 | S39: =S4/S$16 -> 3.7617414e-05 | T39: =T4/T$16 -> 0.00066230738 | U39: =U4/U$16 -> 0.0011068827 | V39: =V4/V$16 -> 0.00069354031 | W39: =W4/W$16 -> 0.00047690352 | ... AB39: =AB4/AB$16 -> 0.00017831011
O40: Agricultural Equipment and Industrial Facilities | P40: =P5/P$16 -> 0.031123835 | Q40: =Q5/Q$16 -> 0.019100353 | R40: =R5/R$16 -> 0.011897261 | S40: =S5/S$16 -> 0.0093605871 | T40: =T5/T$16 -> 0.01379714 | U40: =U5/U$16 -> 0.043417673 | V40: =V5/V$16 -> 0.038106646 | W40: =W5/W$16 -> 0.031144961 | ... AB40: =AB5/AB$16 -> 0.038672989
A41: 2022 | B41: Farmland | C41: 1720317 | E41: 185 | F41: -3077 | G41: - | H41: - | I41: - | J41: - | K41: =SUM(C41:J41) -> 1717425 | O41: Vehicles | P41: =P6/P$16 -> 0.0028937346 | Q41: =Q6/Q$16 -> 0.0012869864 | R41: =R6/R$16 -> 0.001057502 | S41: =S6/S$16 -> 0.00037111026 | T41: =T6/T$16 -> 0.0012806843 | U41: =U6/U$16 -> 0.0072942476 | V41: =V6/V$16 -> 0.0041497487 | W41: =W6/W$16 -> 0.00091559919 | ... AB41: =AB6/AB$16 -> 0.00071065623
A42: 2022 | B42: Soil Improvement and Development | C42: 397786 | E42: 187328 | F42: - | G42: 59 | H42: - | I42: - | J42: -71664 | K42: =SUM(C42:J42) -> 513509 | O42: Furniture and Fixtures | P42: =P7/P$16 -> 0.00038195139 | Q42: =Q7/Q$16 -> 0.0003954802 | R42: =R7/R$16 -> 0.00032756416 | S42: =S7/S$16 -> 0.00053677156 | T42: =T7/T$16 -> 0.00036745215 | U42: =U7/U$16 -> 0.00098225929 | V42: =V7/V$16 -> 0.00077183745 | W42: =W7/W$16 -> 0.0010534948 | ... AB42: =AB7/AB$16 -> 0.0011377883
A43: 2022 | B43: Buildings and Improvements | C43: 382767 | E43: 2442 | F43: -1057 | G43: 85024 | H43: - | I43: -242 | J43: -22175 | K43: =SUM(C43:J43) -> 446759 | O43: Office Equipment and Installations | P43: =P8/P$16 -> 0.00064442253 | Q43: =Q8/Q$16 -> 0.00088033447 | R43: =R8/R$16 -> 0.00055816643 | S43: =S8/S$16 -> 0.00043368538 | T43: =T8/T$16 -> 0.00070996075 | U43: =U8/U$16 -> 0.0017492599 | V43: =V8/V$16 -> 0.00236364 | W43: =W8/W$16 -> 0.0030785112 | ... AB43: =AB8/AB$16 -> 0.0016023913
A44: 2022 | B44: Agricultural Equipment and Industrial Facilities | C44: 708357 | E44: 230228 | F44: -4850 | G44: 35040 | H44: - | I44: -18985 | J44: -105667 | K44: =SUM(C44:J44) -> 844123 | O44: Other | P44: =P9/P$16 -> 0.00014376172 | Q44: =Q9/Q$16 -> 0.0001333163 | R44: =R9/R$16 -> 8.4614689e-05 | S44: =S9/S$16 -> 5.389418e-05 | T44: =T9/T$16 -> 7.9298185e-05 | U44: =U9/U$16 -> 0.00022394454 | V44: =V9/V$16 -> 0.00031965348 | W44: =W9/W$16 -> 0.00026502359 | X44: 0 | Y44: =Y9/Y$16 -> 0.00026779963 | Z44: =Z9/Z$16 -> 0.00029894629 | AA44: =AA9/AA$16 -> 0.00059990554 | AB44: =AB9/AB$16 -> 0.00089321181
A45: 2022 | B45: Vehicles | C45: 59862 | E45: 4797 | F45: -157 | G45: 6906 | H45: - | I45: -4983 | J45: -6715 | K45: =SUM(C45:J45) -> 59710 | O45: Advances to Suppliers | P45: =P10/P$16 -> 0.0064276522 | Q45: =Q10/Q$16 -> 0.0012110185 | R45: 0 | S45: =S10/S$16 -> 0 | T45: =T10/T$16 -> 0 | U45: =U10/U$16 -> 0 | V45: =V10/V$16 -> 0 | W45: =W10/W$16 -> 0 | X45: =X10/X$16 -> 0 | Y45: =Y10/Y$16 -> 0 | Z45: =Z10/Z$16 -> 0 | ... AB45: =AB10/AB$16 -> 0
A46: 2022 | B46: Furniture and Fixtures | C46: 13625 | E46: 4710 | F46: -412 | G46: 635 | H46: - | I46: -245 | J46: -2203 | K46: =SUM(C46:J46) -> 16110 | O46: Construction in Progress | P46: =P11/P$16 -> 0.014186546 | Q46: =Q11/Q$16 -> 0.020659931 | R46: =R11/R$16 -> 0.014300246 | S46: =S11/S$16 -> 0.007134649 | T46: =T11/T$16 -> 0.018108653 | U46: =U11/U$16 -> 0.027372972 | V46: =V11/V$16 -> 0.031074269 | W46: =W11/W$16 -> 0.0094373407 | X46: 0 | Y46: =Y11/Y$16 -> 0.042051016 | Z46: =Z11/Z$16 -> 0.065695591 | AA46: =AA11/AA$16 -> 0.10547759 | AB46: =AB11/AB$16 -> 0.064420156
A47: 2022 | B47: Office Equipment and Installations | C47: 30225 | E47: 13201 | F47: -178 | G47: 1119 | H47: - | I47: -42 | J47: -8529 | K47: =SUM(C47:J47) -> 35796 | O47: Bearer Plants | P47: =P12/P$16 -> 0 | Q47: =Q12/Q$16 -> 0 | R47: 0 | S47: 0 | T47: 0 | U47: 0 | V47: 0 | W47: =W12/W$16 -> 0 | X47: =X12/X$16 -> 0 | Y47: =Y12/Y$16 -> 0 | Z47: =Z12/Z$16 -> 0 | AA47: =AA12/AA$16 -> 0 | AB47: =AB12/AB$16 -> 0
A48: 2022 | B48: Other | C48: 8113 | E48: 910 | F48: -71 | G48: 794 | H48: -272 | I48: - | J48: -120 | K48: =SUM(C48:J48) -> 9354 | O48: Total | P48: =P13/P$16 -> 0.10126645 | Q48: =Q13/Q$16 -> 0.072789956 | R48: =R13/R$16 -> 0.072273655 | S48: =S13/S$16 -> 0.027492181 | T48: =T13/T$16 -> 0.048566974 | U48: =U13/U$16 -> 0.10111644 | V48: =V13/V$16 -> 0.095248118 | W48: =W13/W$16 -> 0.072863078 | ... AB48: =AB13/AB$16 -> 0.31937518
A49: 2022 | B49: Advances to Suppliers | O49: Total Ex Farmland & Construction in Progress | P49: =P48-P37-P46 -> 0.066472261 | Q49: =Q48-Q37-Q46 -> 0.051638096 | R49: =R48-R37-R46 -> 0.026895124 | S49: =S48-S37-S46 -> 0.020356808 | T49: =T48-T37-T46 -> 0.028820237 | U49: =U48-U37-U46 -> 0.072986283 | V49: =V48-V37-V46 -> 0.063071223 | W49: =W48-W37-W46 -> 0.063390308 | ... AB49: =AB48-AB37-AB46 -> 0.099524174
A50: 2022 | B50: Construction in Progress | C50: 77011 | E50: 142892 | F50: - | G50: -129577 | H50: - | I50: - | J50: - | K50: =SUM(C50:J50) -> 90326
A51: 2022 | B51: Bearer Plants
A52: 2022 | B52: Total | C52: =SUM(C41:C50) -> 3398063 | D52: =SUM(D41:D50) -> 0 | E52: =SUM(E41:E50) -> 586693 | F52: =SUM(F41:F50) -> -9802 | G52: =SUM(G41:G50) -> 0 | H52: =SUM(H41:H50) -> -272 | I52: =SUM(I41:I50) -> -24497 | J52: =SUM(J41:J50) -> -217073 | K52: =SUM(K41:K50) -> 3733112
O53: Dep % of Initial Total PPE + (Total Capex/2)
A54: 2021 | B54: Farmland | C54: 1720026 | D54: - | E54: 321 | F54: -10 | G54: -20 | H54: 0 | J54: - | K54: =SUM(C54:J54) -> 1720317 | O54: Farmland | P54: =(IF(P22="-",0,P22))/(P$16+(IF(P13="-",0,P13)/2)) -> 0 | Q54: =(IF(Q22="-",0,Q22))/(Q$16+(IF(Q13="-",0,Q13)/2)) -> 0 | R54: =(IF(R22="-",0,R22))/(R$16+(IF(R13="-",0,R13)/2)) -> 0 | S54: =(IF(S22="-",0,S22))/(S$16+(IF(S13="-",0,S13)/2)) -> 0 | T54: =(IF(T22="-",0,T22))/(T$16+(IF(T13="-",0,T13)/2)) -> 0 | U54: =(IF(U22="-",0,U22))/(U$16+(IF(U13="-",0,U13)/2)) -> 0 | V54: =(IF(V22="-",0,V22))/(V$16+(IF(V13="-",0,V13)/2)) -> 0 | W54: =(IF(W22="-",0,W22))/(W$16+(IF(W13="-",0,W13)/2)) -> 0 | ... AB54: =(IF(AB22="-",0,AB22))/(AB$16+(IF(AB13="-",0,AB13)/2)) -> 0
A55: 2021 | B55: Soil Improvement and Development | C55: 265921 | D55: 26473 | E55: 153372 | F55: - | G55: =785-67 -> 718 | H55: 0 | J55: -48698 | K55: =SUM(C55:J55) -> 397786 | O55: Soil Improvement and Development | P55: =(IF(P23="-",0,P23))/(P$16+(IF(P14="-",0,P14)/2)) -> -0.018408438 | Q55: =(IF(Q23="-",0,Q23))/(Q$16+(IF(Q14="-",0,Q14)/2)) -> -0.012838584 | R55: =(IF(R23="-",0,R23))/(R$16+(IF(R14="-",0,R14)/2)) -> -0.012771008 | S55: =(IF(S23="-",0,S23))/(S$16+(IF(S14="-",0,S14)/2)) -> -0.01110799 | T55: =(IF(T23="-",0,T23))/(T$16+(IF(T14="-",0,T14)/2)) -> -0.010773755 | U55: =(IF(U23="-",0,U23))/(U$16+(IF(U14="-",0,U14)/2)) -> -0.010861119 | V55: =(IF(V23="-",0,V23))/(V$16+(IF(V14="-",0,V14)/2)) -> -0.010150973 | W55: =(IF(W23="-",0,W23))/(W$16+(IF(W14="-",0,W14)/2)) -> -0.011865277 | ... AB55: =(IF(AB23="-",0,AB23))/(AB$16+(IF(AB14="-",0,AB14)/2)) -> -0.028667132
A56: 2021 | B56: Buildings and Improvements | C56: 391212 | D56: 3626 | E56: 1060 | F56: -231 | G56: =8381-26 -> 8355 | H56: 26 | J56: =-20836-445 -> -21281 | K56: =SUM(C56:J56) -> 382767 | O56: Buildings and Improvements | P56: =(IF(P24="-",0,P24))/(P$16+(IF(P15="-",0,P15)/2)) -> -0.0019787472 | Q56: =(IF(Q24="-",0,Q24))/(Q$16+(IF(Q15="-",0,Q15)/2)) -> -0.0025106662 | R56: =(IF(R24="-",0,R24))/(R$16+(IF(R15="-",0,R15)/2)) -> -0.0027635956 | S56: =(IF(S24="-",0,S24))/(S$16+(IF(S15="-",0,S15)/2)) -> -0.003014457 | T56: =(IF(T24="-",0,T24))/(T$16+(IF(T15="-",0,T15)/2)) -> -0.0036592576 | U56: =(IF(U24="-",0,U24))/(U$16+(IF(U15="-",0,U15)/2)) -> -0.0059373627 | V56: =(IF(V24="-",0,V24))/(V$16+(IF(V15="-",0,V15)/2)) -> -0.0062792155 | W56: =(IF(W24="-",0,W24))/(W$16+(IF(W15="-",0,W15)/2)) -> -0.0070114891 | ... AB56: =(IF(AB24="-",0,AB24))/(AB$16+(IF(AB15="-",0,AB15)/2)) -> -0.0072898562
A57: 2021 | B57: Agricultural Equipment and Industrial Facilities | C57: 484291 | D57: =69735+81921 -> 151656 | E57: 171752 | F57: =-45049+32974 -> -12075 | G57: =2796+294 -> 3090 | H57: 8 | J57: =-82858-7607 -> -90465 | K57: =SUM(C57:J57)+100 -> 708357 | O57: Agricultural Equipment and Industrial Facilities | P57: =(IF(P25="-",0,P25))/(P$16+(IF(P16="-",0,P16)/2)) -> -0.012025366 | Q57: =(IF(Q25="-",0,Q25))/(Q$16+(IF(Q16="-",0,Q16)/2)) -> -0.013911817 | R57: =(IF(R25="-",0,R25))/(R$16+(IF(R16="-",0,R16)/2)) -> -0.013127261 | S57: =(IF(S25="-",0,S25))/(S$16+(IF(S16="-",0,S16)/2)) -> -0.012252185 | T57: =(IF(T25="-",0,T25))/(T$16+(IF(T16="-",0,T16)/2)) -> -0.012029001 | U57: =(IF(U25="-",0,U25))/(U$16+(IF(U16="-",0,U16)/2)) -> -0.016152205 | V57: =(IF(V25="-",0,V25))/(V$16+(IF(V16="-",0,V16)/2)) -> -0.014676285 | W57: =(IF(W25="-",0,W25))/(W$16+(IF(W16="-",0,W16)/2)) -> -0.015822452 | ... AB57: =(IF(AB25="-",0,AB25))/(AB$16+(IF(AB16="-",0,AB16)/2)) -> -0.01537011
A58: 2021 | B58: Vehicles | C58: 34458 | D58: 31314 | E58: 3471 | F58: -855 | G58: =10-124 -> -114 | H58: 3 | J58: =-5501-2908 -> -8409 | K58: =SUM(C58:J58)-6 -> 59862 | O58: Vehicles | P58: =(IF(P26="-",0,P26))/(P$16+(IF(P17="-",0,P17)/2)) -> -0.00047672959 | Q58: =(IF(Q26="-",0,Q26))/(Q$16+(IF(Q17="-",0,Q17)/2)) -> -0.00057473692 | R58: =(IF(R26="-",0,R26))/(R$16+(IF(R17="-",0,R17)/2)) -> -0.00054738911 | S58: =(IF(S26="-",0,S26))/(S$16+(IF(S17="-",0,S17)/2)) -> -0.00075930403 | T58: =(IF(T26="-",0,T26))/(T$16+(IF(T17="-",0,T17)/2)) -> -0.00056358364 | U58: =(IF(U26="-",0,U26))/(U$16+(IF(U17="-",0,U17)/2)) -> -0.0010494765 | V58: =(IF(V26="-",0,V26))/(V$16+(IF(V17="-",0,V17)/2)) -> -0.0013779187 | W58: =(IF(W26="-",0,W26))/(W$16+(IF(W17="-",0,W17)/2)) -> -0.0012890664 | ... AB58: =(IF(AB26="-",0,AB26))/(AB$16+(IF(AB17="-",0,AB17)/2)) -> -0.0011685557
A59: 2021 | B59: Furniture and Fixtures | C59: 10025 | D59: 2641 | E59: 3016 | F59: -81 | G59: =-105+16 -> -89 | H59: 0 | J59: =-1765-122 -> -1887 | K59: =SUM(C59:J59) -> 13625 | O59: Furniture and Fixtures | P59: =(IF(P27="-",0,P27))/(P$16+(IF(P18="-",0,P18)/2)) -> -0.00034687815 | Q59: =(IF(Q27="-",0,Q27))/(Q$16+(IF(Q18="-",0,Q18)/2)) -> -0.00029195525 | R59: =(IF(R27="-",0,R27))/(R$16+(IF(R18="-",0,R18)/2)) -> -0.00029052254 | S59: =(IF(S27="-",0,S27))/(S$16+(IF(S18="-",0,S18)/2)) -> -0.00030310955 | T59: =(IF(T27="-",0,T27))/(T$16+(IF(T18="-",0,T18)/2)) -> -0.00036596299 | U59: =(IF(U27="-",0,U27))/(U$16+(IF(U18="-",0,U18)/2)) -> -0.00042296439 | V59: =(IF(V27="-",0,V27))/(V$16+(IF(V18="-",0,V18)/2)) -> -0.00043674003 | W59: =(IF(W27="-",0,W27))/(W$16+(IF(W18="-",0,W18)/2)) -> -0.0004901026 | ... AB59: =(IF(AB27="-",0,AB27))/(AB$16+(IF(AB18="-",0,AB18)/2)) -> -0.00072302347
A60: 2021 | B60: Office Equipment and Installations | C60: 19967 | D60: 795 | E60: 16259 | F60: -106 | G60: =-439-101 -> -540 | H60: 6 | J60: =-6143-13 -> -6156 | K60: =SUM(C60:J60) -> 30225 | O60: Office Equipment and Installations | P60: =(IF(P28="-",0,P28))/(P$16+(IF(P19="-",0,P19)/2)) -> -0.00030640904 | Q60: =(IF(Q28="-",0,Q28))/(Q$16+(IF(Q19="-",0,Q19)/2)) -> -0.00047479968 | R60: =(IF(R28="-",0,R28))/(R$16+(IF(R19="-",0,R19)/2)) -> -0.0005614348 | S60: =(IF(S28="-",0,S28))/(S$16+(IF(S19="-",0,S19)/2)) -> -0.00055485686 | T60: =(IF(T28="-",0,T28))/(T$16+(IF(T19="-",0,T19)/2)) -> -0.00060534671 | U60: =(IF(U28="-",0,U28))/(U$16+(IF(U19="-",0,U19)/2)) -> -0.0007805959 | V60: =(IF(V28="-",0,V28))/(V$16+(IF(V19="-",0,V19)/2)) -> -0.00090329046 | W60: =(IF(W28="-",0,W28))/(W$16+(IF(W19="-",0,W19)/2)) -> -0.0012566912 | ... AB60: =(IF(AB28="-",0,AB28))/(AB$16+(IF(AB19="-",0,AB19)/2)) -> -0.0025199685
A61: 2021 | B61: Other | C61: 7711 | D61: - | E61: 594 | F61: -116 | G61: =1+8 -> 9 | H61: 0 | J61: -85 | K61: =SUM(C61:J61) -> 8113 | O61: Other | P61: =(IF(P29="-",0,P29))/(P$16+(IF(P20="-",0,P20)/2)) -> 0 | Q61: =(IF(Q29="-",0,Q29))/(Q$16+(IF(Q20="-",0,Q20)/2)) -> 0 | R61: =(IF(R29="-",0,R29))/(R$16+(IF(R20="-",0,R20)/2)) -> 0 | S61: =(IF(S29="-",0,S29))/(S$16+(IF(S20="-",0,S20)/2)) -> -4.1234473e-05 | T61: =(IF(T29="-",0,T29))/(T$16+(IF(T20="-",0,T20)/2)) -> 0 | U61: =(IF(U29="-",0,U29))/(U$16+(IF(U20="-",0,U20)/2)) -> -1.8882339e-06 | V61: =(IF(V29="-",0,V29))/(V$16+(IF(V20="-",0,V20)/2)) -> -1.4366449e-06 | W61: =(IF(W29="-",0,W29))/(W$16+(IF(W20="-",0,W20)/2)) -> -1.2157045e-05 | ... AB61: =(IF(AB29="-",0,AB29))/(AB$16+(IF(AB20="-",0,AB20)/2)) -> -5.3529949e-05
A62: 2021 | B62: Advances to Suppliers | O62: Advances to Suppliers | P62: =(IF(P30="-",0,P30))/(P$16+(IF(P21="-",0,P21)/2)) -> 0 | Q62: =(IF(Q30="-",0,Q30))/(Q$16+(IF(Q21="-",0,Q21)/2)) -> 0 | R62: =(IF(R30="-",0,R30))/(R$16+(IF(R21="-",0,R21)/2)) -> 0 | S62: =(IF(S30="-",0,S30))/(S$16+(IF(S21="-",0,S21)/2)) -> 0 | T62: =(IF(T30="-",0,T30))/(T$16+(IF(T21="-",0,T21)/2)) -> 0 | U62: =(IF(U30="-",0,U30))/(U$16+(IF(U21="-",0,U21)/2)) -> 0 | V62: =(IF(V30="-",0,V30))/(V$16+(IF(V21="-",0,V21)/2)) -> 0 | W62: =(IF(W30="-",0,W30))/(W$16+(IF(W21="-",0,W21)/2)) -> 0 | ... AB62: =(IF(AB30="-",0,AB30))/(AB$16+(IF(AB21="-",0,AB21)/2)) -> 0
A63: 2021 | B63: Construction in Progress | C63: 10833 | D63: 2552 | E63: 75039 | F63: - | G63: -11409 | H63: -4 | J63: - | K63: =SUM(C63:J63) -> 77011 | O63: Construction in Progress | P63: =(IF(P31="-",0,P31))/(P$16+(IF(P22="-",0,P22)/2)) -> 0 | Q63: =(IF(Q31="-",0,Q31))/(Q$16+(IF(Q22="-",0,Q22)/2)) -> 0 | R63: =(IF(R31="-",0,R31))/(R$16+(IF(R22="-",0,R22)/2)) -> 0 | S63: =(IF(S31="-",0,S31))/(S$16+(IF(S22="-",0,S22)/2)) -> 0 | T63: =(IF(T31="-",0,T31))/(T$16+(IF(T22="-",0,T22)/2)) -> 0 | U63: =(IF(U31="-",0,U31))/(U$16+(IF(U22="-",0,U22)/2)) -> 0 | V63: =(IF(V31="-",0,V31))/(V$16+(IF(V22="-",0,V22)/2)) -> 0 | W63: =(IF(W31="-",0,W31))/(W$16+(IF(W22="-",0,W22)/2)) -> 0 | ... AB63: =(IF(AB31="-",0,AB31))/(AB$16+(IF(AB22="-",0,AB22)/2)) -> 0
A64: 2021 | B64: Bearer Plants | O64: Bearer Plants | P64: =(IF(P32="-",0,P32))/(P$16+(IF(P23="-",0,P23)/2)) -> 0 | Q64: =(IF(Q32="-",0,Q32))/(Q$16+(IF(Q23="-",0,Q23)/2)) -> 0 | R64: =(IF(R32="-",0,R32))/(R$16+(IF(R23="-",0,R23)/2)) -> 0 | S64: =(IF(S32="-",0,S32))/(S$16+(IF(S23="-",0,S23)/2)) -> -0.00077073548 | T64: =(IF(T32="-",0,T32))/(T$16+(IF(T23="-",0,T23)/2)) -> -0.00052927194 | U64: =(IF(U32="-",0,U32))/(U$16+(IF(U23="-",0,U23)/2)) -> -0.00026807442 | V64: =(IF(V32="-",0,V32))/(V$16+(IF(V23="-",0,V23)/2)) -> 0 | W64: =(IF(W32="-",0,W32))/(W$16+(IF(W23="-",0,W23)/2)) -> 0 | ... AB64: =(IF(AB32="-",0,AB32))/(AB$16+(IF(AB23="-",0,AB23)/2)) -> 0
A65: 2021 | B65: Total | C65: =SUM(C54:C63) -> 2944444 | D65: =SUM(D54:D63) -> 219057 | E65: =SUM(E54:E63) -> 424884 | F65: =SUM(F54:F64) -> -13474 | G65: =SUM(G55:G64) -> 20 | H65: =SUM(H54:H63) -> 39 | I65: =SUM(I54:I63) -> 0 | J65: =SUM(J54:J63) -> -176981 | K65: =SUM(K54:K64) -> 3398063 | O65: Total | P65: =(IF(P33="-",0,P33))/(P$16+(IF(P24="-",0,P24)/2)) -> -0.039841374 | Q65: =(IF(Q33="-",0,Q33))/(Q$16+(IF(Q24="-",0,Q24)/2)) -> -0.037900097 | R65: =(IF(R33="-",0,R33))/(R$16+(IF(R24="-",0,R24)/2)) -> -0.036950689 | S65: =(IF(S33="-",0,S33))/(S$16+(IF(S24="-",0,S24)/2)) -> -0.035347816 | T65: =(IF(T33="-",0,T33))/(T$16+(IF(T24="-",0,T24)/2)) -> -0.034879443 | U65: =(IF(U33="-",0,U33))/(U$16+(IF(U24="-",0,U24)/2)) -> -0.04423139 | V65: =(IF(V33="-",0,V33))/(V$16+(IF(V24="-",0,V24)/2)) -> -0.042008291 | W65: =(IF(W33="-",0,W33))/(W$16+(IF(W24="-",0,W24)/2)) -> -0.046480597 | ... AB65: =(IF(AB33="-",0,AB33))/(AB$16+(IF(AB24="-",0,AB24)/2)) -> -0.064479268
A67: 2020 | B67: Farmland | C67: 1719924 | D67: 0 | E67: 102 | F67: 0 | G67: 0 | H67: 0 | I67: 0 | J67: 0 | K67: =SUM(C67:J67) -> 1720026
A68: 2020 | B68: Soil Improvement and Development | C68: 223978 | D68: 0 | E68: 76166 | F68: 0 | G68: -63 | H68: 0 | I68: 0 | J68: -34160 | K68: =SUM(C68:J68) -> 265921
A69: 2020 | B69: Buildings and Improvements | C69: 376684 | D69: 0 | E69: 1373 | F69: -73 | G69: 33414 | H69: 0 | I69: 0 | J69: -20186 | K69: =SUM(C69:J69) -> 391212 | O69: Dep / (Each PPE Item + (Item Capex/2))
A70: 2020 | B70: Agricultural Equipment and Industrial Facilities | C70: 467316 | D70: 0 | E70: 89666 | F70: -6908 | G70: 2525 | H70: 21 | I70: 0 | J70: -68329 | K70: =SUM(C70:J70) -> 484291 | O70: Farmland | P70: =(IF(P22="-",0,P22))/((IF(P81="-",0,P81))+(IF(P2="-",0,P2)/2)) -> 0 | Q70: =(IF(Q22="-",0,Q22))/((IF(Q81="-",0,Q81))+(IF(Q2="-",0,Q2)/2)) -> 0 | R70: =(IF(R22="-",0,R22))/((IF(R81="-",0,R81))+(IF(R2="-",0,R2)/2)) -> 0 | S70: =(IF(S22="-",0,S22))/((IF(S81="-",0,S81))+(IF(S2="-",0,S2)/2)) -> 0 | T70: =(IF(T22="-",0,T22))/((IF(T81="-",0,T81))+(IF(T2="-",0,T2)/2)) -> 0 | U70: =(IF(U22="-",0,U22))/((IF(U81="-",0,U81))+(IF(U2="-",0,U2)/2)) -> 0 | V70: =(IF(V22="-",0,V22))/((IF(V81="-",0,V81))+(IF(V2="-",0,V2)/2)) -> 0 | W70: =(IF(W22="-",0,W22))/((IF(W81="-",0,W81))+(IF(W2="-",0,W2)/2)) -> 0 | ... AB70: =(IF(AB22="-",0,AB22))/((IF(AB81="-",0,AB81))+(IF(AB2="-",0,AB2)/2)) -> 0
A71: 2020 | B71: Vehicles | C71: 41043 | D71: 0 | E71: 2636 | F71: -755 | G71: -35 | H71: -2822 | I71: 0 | J71: -5609 | K71: =SUM(C71:J71) -> 34458 | O71: Soil Improvement and Development | P71: =(IF(P23="-",0,P23))/((IF(P82="-",0,P82))+(IF(P3="-",0,P3)/2)) -> -0.26806982 | Q71: =(IF(Q23="-",0,Q23))/((IF(Q82="-",0,Q82))+(IF(Q3="-",0,Q3)/2)) -> -0.1764295 | R71: =(IF(R23="-",0,R23))/((IF(R82="-",0,R82))+(IF(R3="-",0,R3)/2)) -> -0.16260542 | S71: =(IF(S23="-",0,S23))/((IF(S82="-",0,S82))+(IF(S3="-",0,S3)/2)) -> -0.1482404 | T71: =(IF(T23="-",0,T23))/((IF(T82="-",0,T82))+(IF(T3="-",0,T3)/2)) -> -0.14393395 | U71: =(IF(U23="-",0,U23))/((IF(U82="-",0,U82))+(IF(U3="-",0,U3)/2)) -> -0.13561592 | V71: =(IF(V23="-",0,V23))/((IF(V82="-",0,V82))+(IF(V3="-",0,V3)/2)) -> -0.123378 | W71: =(IF(W23="-",0,W23))/((IF(W82="-",0,W82))+(IF(W3="-",0,W3)/2)) -> -0.13035133 | ... AB71: =(IF(AB23="-",0,AB23))/((IF(AB82="-",0,AB82))+(IF(AB3="-",0,AB3)/2)) -> -0.16469273
A72: 2020 | B72: Furniture and Fixtures | C72: 8426 | D72: 0 | E72: 3033 | F72: -103 | G72: 80 | H72: 0 | I72: 0 | J72: -1411 | K72: =SUM(C72:J72) -> 10025 | O72: Buildings and Improvements | P72: =(IF(P24="-",0,P24))/((IF(P83="-",0,P83))+(IF(P4="-",0,P4)/2)) -> -0.030947379 | Q72: =(IF(Q24="-",0,Q24))/((IF(Q83="-",0,Q83))+(IF(Q4="-",0,Q4)/2)) -> -0.037744933 | R72: =(IF(R24="-",0,R24))/((IF(R83="-",0,R83))+(IF(R4="-",0,R4)/2)) -> -0.04007214 | S72: =(IF(S24="-",0,S24))/((IF(S83="-",0,S83))+(IF(S4="-",0,S4)/2)) -> -0.040542315 | T72: =(IF(T24="-",0,T24))/((IF(T83="-",0,T83))+(IF(T4="-",0,T4)/2)) -> -0.043579756 | U72: =(IF(U24="-",0,U24))/((IF(U83="-",0,U83))+(IF(U4="-",0,U4)/2)) -> -0.0637446 | V72: =(IF(V24="-",0,V24))/((IF(V83="-",0,V83))+(IF(V4="-",0,V4)/2)) -> -0.057754852 | W72: =(IF(W24="-",0,W24))/((IF(W83="-",0,W83))+(IF(W4="-",0,W4)/2)) -> -0.053491198 | ... AB72: =(IF(AB24="-",0,AB24))/((IF(AB83="-",0,AB83))+(IF(AB4="-",0,AB4)/2)) -> -0.062412784
A73: 2020 | B73: Office Equipment and Installations | C73: 14756 | D73: 0 | E73: 8863 | F73: -45 | G73: 12 | H73: -1 | I73: 0 | J73: -3618 | K73: =SUM(C73:J73) -> 19967 | O73: Agricultural Equipment and Industrial Facilities | P73: =(IF(P25="-",0,P25))/((IF(P84="-",0,P84))+(IF(P5="-",0,P5)/2)) -> -0.10782237 | Q73: =(IF(Q25="-",0,Q25))/((IF(Q84="-",0,Q84))+(IF(Q5="-",0,Q5)/2)) -> -0.1285015 | R73: =(IF(R25="-",0,R25))/((IF(R84="-",0,R84))+(IF(R5="-",0,R5)/2)) -> -0.1286099 | S73: =(IF(S25="-",0,S25))/((IF(S84="-",0,S84))+(IF(S5="-",0,S5)/2)) -> -0.12474084 | T73: =(IF(T25="-",0,T25))/((IF(T84="-",0,T84))+(IF(T5="-",0,T5)/2)) -> -0.12726748 | U73: =(IF(U25="-",0,U25))/((IF(U84="-",0,U84))+(IF(U5="-",0,U5)/2)) -> -0.15659014 | V73: =(IF(V25="-",0,V25))/((IF(V84="-",0,V84))+(IF(V5="-",0,V5)/2)) -> -0.13703552 | W73: =(IF(W25="-",0,W25))/((IF(W84="-",0,W84))+(IF(W5="-",0,W5)/2)) -> -0.13341625 | ... AB73: =(IF(AB25="-",0,AB25))/((IF(AB84="-",0,AB84))+(IF(AB5="-",0,AB5)/2)) -> -0.10827244
A74: 2020 | B74: Other | C74: 6831 | D74: 0 | E74: 763 | F74: -265 | G74: 417 | H74: 0 | I74: 0 | J74: -35 | K74: =SUM(C74:J74) -> 7711 | O74: Vehicles | P74: =(IF(P26="-",0,P26))/((IF(P85="-",0,P85))+(IF(P6="-",0,P6)/2)) -> -0.088738654 | Q74: =(IF(Q26="-",0,Q26))/((IF(Q85="-",0,Q85))+(IF(Q6="-",0,Q6)/2)) -> -0.096656585 | R74: =(IF(R26="-",0,R26))/((IF(R85="-",0,R85))+(IF(R6="-",0,R6)/2)) -> -0.092427026 | S74: =(IF(S26="-",0,S26))/((IF(S85="-",0,S85))+(IF(S6="-",0,S6)/2)) -> -0.1287141 | T74: =(IF(T26="-",0,T26))/((IF(T85="-",0,T85))+(IF(T6="-",0,T6)/2)) -> -0.097619973 | U74: =(IF(U26="-",0,U26))/((IF(U85="-",0,U85))+(IF(U6="-",0,U6)/2)) -> -0.13244413 | V74: =(IF(V26="-",0,V26))/((IF(V85="-",0,V85))+(IF(V6="-",0,V6)/2)) -> -0.13619132 | W74: =(IF(W26="-",0,W26))/((IF(W85="-",0,W85))+(IF(W6="-",0,W6)/2)) -> -0.13240953 | ... AB74: =(IF(AB26="-",0,AB26))/((IF(AB85="-",0,AB85))+(IF(AB6="-",0,AB6)/2)) -> -0.087748954
A75: 2020 | B75: Advances to Suppliers | O75: Furniture and Fixtures | P75: =(IF(P27="-",0,P27))/((IF(P86="-",0,P86))+(IF(P7="-",0,P7)/2)) -> -0.10855799 | Q75: =(IF(Q27="-",0,Q27))/((IF(Q86="-",0,Q86))+(IF(Q7="-",0,Q7)/2)) -> -0.093222354 | R75: =(IF(R27="-",0,R27))/((IF(R86="-",0,R86))+(IF(R7="-",0,R7)/2)) -> -0.093218364 | S75: =(IF(S27="-",0,S27))/((IF(S86="-",0,S86))+(IF(S7="-",0,S7)/2)) -> -0.09528141 | T75: =(IF(T27="-",0,T27))/((IF(T86="-",0,T86))+(IF(T7="-",0,T7)/2)) -> -0.10782647 | U75: =(IF(U27="-",0,U27))/((IF(U86="-",0,U86))+(IF(U7="-",0,U7)/2)) -> -0.11123802 | V75: =(IF(V27="-",0,V27))/((IF(V86="-",0,V86))+(IF(V7="-",0,V7)/2)) -> -0.12384784 | W75: =(IF(W27="-",0,W27))/((IF(W86="-",0,W86))+(IF(W7="-",0,W7)/2)) -> -0.14191602 | ... AB75: =(IF(AB27="-",0,AB27))/((IF(AB86="-",0,AB86))+(IF(AB7="-",0,AB7)/2)) -> -0.13536303
A76: 2020 | B76: Construction in Progress | C76: 20031 | D76: 0 | E76: 27170 | F76: -18 | G76: -36350 | H76: 0 | I76: 0 | J76: 0 | K76: =SUM(C76:J76) -> 10833 | O76: Office Equipment and Installations | P76: =(IF(P28="-",0,P28))/((IF(P87="-",0,P87))+(IF(P8="-",0,P8)/2)) -> -0.11599066 | Q76: =(IF(Q28="-",0,Q28))/((IF(Q87="-",0,Q87))+(IF(Q8="-",0,Q8)/2)) -> -0.15874004 | R76: =(IF(R28="-",0,R28))/((IF(R87="-",0,R87))+(IF(R8="-",0,R8)/2)) -> -0.17830575 | S76: =(IF(S28="-",0,S28))/((IF(S87="-",0,S87))+(IF(S8="-",0,S8)/2)) -> -0.17946768 | T76: =(IF(T28="-",0,T28))/((IF(T87="-",0,T87))+(IF(T8="-",0,T8)/2)) -> -0.19114795 | U76: =(IF(U28="-",0,U28))/((IF(U87="-",0,U87))+(IF(U8="-",0,U8)/2)) -> -0.20667933 | V76: =(IF(V28="-",0,V28))/((IF(V87="-",0,V87))+(IF(V8="-",0,V8)/2)) -> -0.18660731 | W76: =(IF(W28="-",0,W28))/((IF(W87="-",0,W87))+(IF(W8="-",0,W8)/2)) -> -0.18856026 | ... AB76: =(IF(AB28="-",0,AB28))/((IF(AB87="-",0,AB87))+(IF(AB8="-",0,AB8)/2)) -> -0.3001792
A77: 2020 | B77: Bearer Plants | O77: Other | P77: =(IF(P29="-",0,P29))/((IF(P88="-",0,P88))+(IF(P9="-",0,P9)/2)) -> 0 | Q77: =(IF(Q29="-",0,Q29))/((IF(Q88="-",0,Q88))+(IF(Q9="-",0,Q9)/2)) -> 0 | R77: =(IF(R29="-",0,R29))/((IF(R88="-",0,R88))+(IF(R9="-",0,R9)/2)) -> 0 | S77: =(IF(S29="-",0,S29))/((IF(S88="-",0,S88))+(IF(S9="-",0,S9)/2)) -> -0.02090784 | T77: =(IF(T29="-",0,T29))/((IF(T88="-",0,T88))+(IF(T9="-",0,T9)/2)) -> 0 | U77: =(IF(U29="-",0,U29))/((IF(U88="-",0,U88))+(IF(U9="-",0,U9)/2)) -> -0.00086602581 | V77: =(IF(V29="-",0,V29))/((IF(V88="-",0,V88))+(IF(V9="-",0,V9)/2)) -> -0.00061919505 | W77: =(IF(W29="-",0,W29))/((IF(W88="-",0,W88))+(IF(W9="-",0,W9)/2)) -> -0.0048526863 | ... AB77: =(IF(AB29="-",0,AB29))/((IF(AB88="-",0,AB88))+(IF(AB9="-",0,AB9)/2)) -> -0.016695933
A78: 2020 | B78: Total | C78: =SUM(C67:C76) -> 2878989 | D78: =SUM(D67:D76) -> 0 | E78: =SUM(E67:E76) -> 209772 | F78: =SUM(F67:F76) -> -8167 | G78: =SUM(G67:G76) -> 0 | H78: =SUM(H67:H76) -> -2802 | I78: =SUM(I67:I76) -> 0 | J78: =SUM(J67:J76) -> -133348 | K78: =SUM(K67:K76) -> 2944444
A80: 2019 | B80: Farmland | C80: 1759560 | E80: 3070 | F80: -42732 | G80: 26 | H80: - | I80: - | J80: - | K80: =SUM(C80:J80) -> 1719924 | O80: Initial PPE
A81: 2019 | B81: Soil Improvement and Development | C81: 205875 | E81: 46403 | F81: - | G81: -35 | H81: 2 | I81: - | J81: -28263 | K81: =SUM(C81:J81) -> 223982 | O81: Farmland | P81: {=_xlfn._xlws.FILTER($C:$C,$A:$A=P$1)} -> 1825873 | Q81: {=_xlfn._xlws.FILTER($C:$C,$A:$A=Q$1)} -> 1855513 | R81: {=_xlfn._xlws.FILTER($C:$C,$A:$A=R$1)} -> 1846737 | S81: {=_xlfn._xlws.FILTER($C:$C,$A:$A=S$1)} -> 1864703 | T81: {=_xlfn._xlws.FILTER($C:$C,$A:$A=T$1)} -> 1820821 | U81: {=_xlfn._xlws.FILTER($C:$C,$A:$A=U$1)} -> 1757566 | V81: {=_xlfn._xlws.FILTER($C:$C,$A:$A=V$1)} -> 1759560 | W81: {=_xlfn._xlws.FILTER($C:$C,$A:$A=W$1)} -> 1719924 | ... AB81: {=_xlfn._xlws.FILTER($C:$C,$A:$A=AB$1)} -> 2466270
A82: 2019 | B82: Buildings and Improvements | C82: 301745 | E82: 1931 | F82: - | G82: 86136 | H82: =358+3997 -> 4355 | I82: - | J82: -17483 | K82: =SUM(C82:J82) -> 376684 | O82: Soil Improvement and Development | P82: 146161 | Q82: 157308 | R82: 198515 | S82: 193944 | T82: 185044 | U82: 187957 | V82: 205875 | W82: 223978 | X82: 265921 | Y82: 397786 | Z82: 513509 | AA82: 613121 | AB82: 790417
A83: 2019 | B83: Agricultural Equipment and Industrial Facilities | C83: 394236 | E83: 106099 | F83: -11023 | G83: 41585 | H83: -2287 | I83: - | J83: -61294 | K83: =SUM(C83:J83) -> 467316 | O83: Buildings and Improvements | P83: 165657 | Q83: 178280 | R83: 189807 | S83: 205511 | T83: 224651 | U83: 245175 | V83: 301745 | W83: 376684 | X83: 391212 | Y83: 382767 | Z83: 446759 | AA83: 533164 | AB83: 632288
A84: 2019 | B84: Vehicles | C84: 36957 | E84: 11554 | F84: -1055 | G84: -571 | H84: -22 | I84: - | J84: -5820 | K84: =SUM(C84:J84) -> 41043 | O84: Agricultural Equipment and Industrial Facilities | P84: 393680 | Q84: 410435 | R84: 405220 | S84: 394385 | T84: 362290 | U84: 352222 | V84: 394236 | W84: 467316 | X84: 484291 | Y84: 708357 | Z84: 844123 | AA84: 862913 | AB84: 1048834
A85: 2019 | B85: Furniture and Fixtures | C85: 8744 | E85: 2149 | F85: -36 | G85: 109 | H85: -1324 | I85: - | J85: -1216 | K85: =SUM(C85:J85) -> 8426 | O85: Vehicles | P85: 17398 | Q85: 22409 | R85: 23039 | S85: 23719 | T85: 21431 | U85: 22356 | V85: 36957 | W85: 41043 | X85: 34458 | Y85: 59862 | Z85: 59710 | AA85: 104587 | AB85: 117575
A86: 2019 | B86: Office Equipment and Installations | C86: 10187 | E86: 6581 | F86: -61 | G86: 182 | H86: 382 | I86: - | J86: -2515 | K86: =SUM(C86:J86) -> 14756 | O86: Furniture and Fixtures | P86: 7795 | Q86: 7879 | R86: 8131 | S86: 8053 | T86: 8623 | U86: 8768 | V86: 8744 | W86: 8426 | X86: 10025 | Y86: 13625 | Z86: 16110 | AA86: 20224 | AB86: 25855
A87: 2019 | B87: Other | C87: 6015 | E87: 890 | F87: -53 | G87: 1 | H87: -18 | I87: - | J87: -4 | K87: =SUM(C87:J87) -> 6831 | O87: Office Equipment and Installations | P87: 6018 | Q87: 6850 | R87: 7902 | S87: 7948 | T87: 7553 | U87: 7685 | V87: 10187 | W87: 14756 | X87: 19967 | Y87: 30225 | Z87: 35796 | AA87: 41837 | AB87: 41139
A88: 2019 | B88: Advances to Suppliers | O88: Other | P88: 4891 | Q88: 4936 | R88: 5202 | S88: 5378 | T88: 5392 | U88: 5477 | V88: 6015 | W88: 6831 | X88: 7711 | Y88: 8113 | Z88: 9354 | AA88: 10278 | AB88: 14950
A89: 2019 | B89: Construction in Progress | C89: 60946 | E89: 86519 | F89: - | G89: -127433 | H89: -1 | I89: - | J89: - | K89: =SUM(C89:J89) -> 20031 | O89: Advances to Suppliers | P89: 9662 | Q89: 5638 | R89: 1645 | S89: 0 | T89: 0 | U89: 0 | V89: 0 | W89: 0 | X89: 0 | Y89: 0 | Z89: 0 | AA89: 0 | AB89: 0
A90: 2019 | B90: Bearer Plants | C90: 0 | E90: - | F90: - | G90: - | H90: - | I90: - | J90: - | K90: =SUM(C90:J90) -> 0 | O90: Construction in Progress | P90: 17436 | Q90: 36095 | R90: 61613 | S90: 56797 | T90: 48139 | U90: 60065 | V90: 60946 | W90: 20031 | X90: 10833 | Y90: 77011 | Z90: 90326 | AA90: 126288 | AB90: 280200
A91: 2019 | B91: Total | C91: =SUM(C80:C90) -> 2784265 | D91: =SUM(D80:D90) -> 0 | E91: =SUM(E80:E90) -> 265196 | F91: =SUM(F80:F90) -> -54960 | G91: =SUM(G80:G90) -> 0 | H91: =SUM(H80:H90) -> 1087 | I91: =SUM(I80:I90) -> 0 | J91: =SUM(J80:J90) -> -116595 | K91: =SUM(K80:K90) -> 2878993 | O91: Bearer Plants | P91: 0 | Q91: 0 | R91: 5848 | S91: 4239 | T91: 2120 | U91: 706 | V91: 0 | W91: 0 | X91: 0 | Y91: 0 | Z91: 0 | AA91: 0 | AB91: 0
O92: Total | P92: 2594571 | Q92: 2685343 | R92: 2753659 | S92: 2764677 | T92: 2686064 | U92: 2647977 | V92: 2784265 | W92: 2878989 | X92: 2944444 | Y92: 3398063 | Z92: 3733112 | AA92: 4395692 | AB92: 5417528
A93: 2018 | B93: Farmland | C93: 1757566 | E93: 2005 | F93: -11 | G93: - | H93: - | I93: - | J93: - | K93: =SUM(C93:J93) -> 1759560
A94: 2018 | B94: Soil Improvement and Development | C94: 187957 | E94: 48225 | F94: -1547 | G94: - | H94: - | I94: - | J94: -28760 | K94: =SUM(C94:J94) -> 205875 | O94: Ending PPE
A95: 2018 | B95: Buildings and Improvements | C95: 245175 | E95: 2931 | F95: -967 | G95: 70328 | H95: - | I95: - | J95: -15722 | K95: =SUM(C95:J95) -> 301745 | O95: Farmland | P95: {=_xlfn._xlws.FILTER($K:$K,$A:$A=P$1)} -> 1855513 | Q95: {=_xlfn._xlws.FILTER($K:$K,$A:$A=Q$1)} -> 1846737 | R95: {=_xlfn._xlws.FILTER($K:$K,$A:$A=R$1)} -> 1864703 | S95: {=_xlfn._xlws.FILTER($K:$K,$A:$A=S$1)} -> 1820821 | T95: {=_xlfn._xlws.FILTER($K:$K,$A:$A=T$1)} -> 1757566 | U95: {=_xlfn._xlws.FILTER($K:$K,$A:$A=U$1)} -> 1759560 | V95: {=_xlfn._xlws.FILTER($K:$K,$A:$A=V$1)} -> 1719924 | W95: {=_xlfn._xlws.FILTER($K:$K,$A:$A=W$1)} -> 1720026 | ... AB95: {=_xlfn._xlws.FILTER($K:$K,$A:$A=AB$1)} -> 3315500
A96: 2018 | B96: Agricultural Equipment and Industrial Facilities | C96: 352222 | E96: 114969 | F96: -9115 | G96: 316 | H96: - | I96: - | J96: -64156 | K96: =SUM(C96:J96) -> 394236 | O96: Soil Improvement and Development | P96: 157308 | Q96: 198515 | R96: 193944 | S96: 185044 | T96: 187957 | U96: 205875 | V96: 223982 | W96: 265921 | X96: 397786 | Y96: 513509 | Z96: 613121 | AA96: 790417 | AB96: 1052113
A97: 2018 | B97: Vehicles | C97: 22356 | E97: 19315 | F97: =-1664+1190 -> -474 | G97: - | H97: - | I97: - | J97: -4240 | K97: =SUM(C97:J97) -> 36957 | O97: Buildings and Improvements | P97: 178280 | Q97: 189807 | R97: 205511 | S97: 224651 | T97: 245175 | U97: 301745 | V97: 376684 | W97: 391212 | X97: 382767 | Y97: 446759 | Z97: 533164 | AA97: 632288 | AB97: 797295
A98: 2018 | B98: Furniture and Fixtures | C98: 8768 | E98: 2601 | F98: =-3305+1800 -> -1505 | G98: - | H98: - | I98: - | J98: -1120 | K98: =SUM(C98:J98) -> 8744 | O98: Agricultural Equipment and Industrial Facilities | P98: 410435 | Q98: 405220 | R98: 394385 | S98: 362290 | T98: 352222 | U98: 394236 | V98: 467316 | W98: 484291 | X98: 708357 | Y98: 844123 | Z98: 862913 | AA98: 1048834 | AB98: 1409647
A99: 2018 | B99: Office Equipment and Installations | C99: 7685 | E99: 4632 | F99: =-305+233 -> -72 | G99: 9 | H99: - | I99: - | J99: -2067 | K99: =SUM(C99:J99) -> 10187 | O99: Vehicles | P99: 22409 | Q99: 23039 | R99: 23719 | S99: 21431 | T99: 22356 | U99: 36957 | V99: 41043 | W99: 34458 | X99: 59862 | Y99: 59710 | Z99: 104587 | AA99: 117575 | AB99: 123837
A100: 2018 | B100: Other | C100: 5477 | E100: 593 | F100: -50 | G100: - | H100: - | I100: - | J100: -5 | K100: =SUM(C100:J100) -> 6015 | O100: Furniture and Fixtures | P100: 7879 | Q100: 8131 | R100: 8053 | S100: 8623 | T100: 8768 | U100: 8744 | V100: 8426 | W100: 10025 | X100: 13625 | Y100: 16110 | Z100: 20224 | AA100: 25855 | AB100: 29100
A101: 2018 | B101: Advances to Suppliers | O101: Office Equipment and Installations | P101: 6850 | Q101: 7902 | R101: 7948 | S101: 7553 | T101: 7685 | U101: 10187 | V101: 14756 | W101: 19967 | X101: 30225 | Y101: 35796 | Z101: 41837 | AA101: 41139 | AB101: 35871
A102: 2018 | B102: Construction in Progress | C102: 60065 | E102: 72483 | F102: -949 | G102: -70653 | H102: - | I102: - | J102: - | K102: =SUM(C102:J102) -> 60946 | O102: Other | P102: 4936 | Q102: 5202 | R102: 5378 | S102: 5392 | T102: 5477 | U102: 6015 | V102: 6831 | W102: 7711 | X102: 8113 | Y102: 9354 | Z102: 10278 | AA102: 14950 | AB102: 18512
...
